{
  "hits": 14,
  "took": 31,
  "items": [
    {
      "meta": {
        "concept-type": "granule",
        "concept-id": "G1647446031-PODAAC",
        "revision-id": 1,
        "native-id": "GRD-3_2018152-2018181_GRFO_GFZOP_BA01_0600_OCN_v02.nc",
        "provider-id": "PODAAC",
        "format": "application/echo10+xml",
        "revision-date": "2019-10-23T19:42:58Z"
      },
      "umm": {
        "TemporalExtent": {
          "RangeDateTime": {
            "BeginningDateTime": "2018-06-01T00:00:00.000Z",
            "EndingDateTime": "2018-06-30T23:59:59.999Z"
          }
        },
        "OrbitCalculatedSpatialDomains": [
          {}
        ],
        "GranuleUR": "GRD-3_2018152-2018181_GRFO_GFZOP_BA01_0600_OCN_v02.nc",
        "SpatialExtent": {
          "HorizontalSpatialDomain": {
            "Geometry": {
              "BoundingRectangles": [
                {
                  "WestBoundingCoordinate": 0.0,
                  "EastBoundingCoordinate": 180.0,
                  "NorthBoundingCoordinate": 0.0,
                  "SouthBoundingCoordinate": 0.0
                },
                {
                  "WestBoundingCoordinate": -180.0,
                  "EastBoundingCoordinate": 0.0,
                  "NorthBoundingCoordinate": 0.0,
                  "SouthBoundingCoordinate": 0.0
                }
              ]
            }
          }
        },
        "ProviderDates": [
          {
            "Date": "2019-10-05T23:04:15.240Z",
            "Type": "Insert"
          },
          {
            "Date": "2019-10-23T19:42:57.407Z",
            "Type": "Update"
          }
        ],
        "CollectionReference": {
          "ShortName": "TELLUS_GRFO_L3_GFZ_RL06_OCN_v02",
          "Version": "RL06 v02"
        },
        "RelatedUrls": [
          {
            "URL": "https://podaac-tools.jpl.nasa.gov/drive/files/allData/tellus/L3/gracefo/ocean_mass/RL06/v02/GFZ//GRD-3_2018152-2018181_GRFO_GFZOP_BA01_0600_OCN_v02.nc",
            "Type": "GET DATA",
            "Description": "The HTTP location for the granule."
          },
          {
            "URL": "https://podaac-opendap.jpl.nasa.gov/opendap/allData/tellus/L3/gracefo/ocean_mass/RL06/v02/GFZ//GRD-3_2018152-2018181_GRFO_GFZOP_BA01_0600_OCN_v02.nc.html",
            "Type": "VIEW RELATED INFORMATION",
            "Description": "The OPENDAP location for the granule.",
            "MimeType": "text/html"
          }
        ],
        "DataGranule": {
          "DayNightFlag": "Unspecified",
          "ProductionDateTime": "2018-06-01T00:00:00.000Z",
          "ArchiveAndDistributionInformation": [
            {
              "Name": "Not provided",
              "Size": 0.5435342788696289,
              "SizeUnit": "MB"
            }
          ]
        },
        "MetadataSpecification": {
          "URL": "https://cdn.earthdata.nasa.gov/umm/granule/v1.6",
          "Name": "UMM-G",
          "Version": "1.6"
        }
      }
    },
    {
      "meta": {
        "concept-type": "granule",
        "concept-id": "G1647446038-PODAAC",
        "revision-id": 1,
        "native-id": "GRD-3_2018182-2018199_GRFO_GFZOP_BA01_0600_OCN_v02.nc",
        "provider-id": "PODAAC",
        "format": "application/echo10+xml",
        "revision-date": "2019-10-23T19:43:00Z"
      },
      "umm": {
        "TemporalExtent": {
          "RangeDateTime": {
            "BeginningDateTime": "2018-07-01T00:00:00.000Z",
            "EndingDateTime": "2018-07-18T23:59:59.999Z"
          }
        },
        "OrbitCalculatedSpatialDomains": [
          {}
        ],
        "GranuleUR": "GRD-3_2018182-2018199_GRFO_GFZOP_BA01_0600_OCN_v02.nc",
        "SpatialExtent": {
          "HorizontalSpatialDomain": {
            "Geometry": {
              "BoundingRectangles": [
                {
                  "WestBoundingCoordinate": 0.0,
                  "EastBoundingCoordinate": 180.0,
                  "NorthBoundingCoordinate": 0.0,
                  "SouthBoundingCoordinate": 0.0
                },
                {
                  "WestBoundingCoordinate": -180.0,
                  "EastBoundingCoordinate": 0.0,
                  "NorthBoundingCoordinate": 0.0,
                  "SouthBoundingCoordinate": 0.0
                }
              ]
            }
          }
        },
        "ProviderDates": [
          {
            "Date": "2019-10-05T23:03:56.336Z",
            "Type": "Insert"
          },
          {
            "Date": "2019-10-23T19:43:00.257Z",
            "Type": "Update"
          }
        ],
        "CollectionReference": {
          "ShortName": "TELLUS_GRFO_L3_GFZ_RL06_OCN_v02",
          "Version": "RL06 v02"
        },
        "RelatedUrls": [
          {
            "URL": "https://podaac-tools.jpl.nasa.gov/drive/files/allData/tellus/L3/gracefo/ocean_mass/RL06/v02/GFZ//GRD-3_2018182-2018199_GRFO_GFZOP_BA01_0600_OCN_v02.nc",
            "Type": "GET DATA",
            "Description": "The HTTP location for the granule."
          },
          {
            "URL": "https://podaac-opendap.jpl.nasa.gov/opendap/allData/tellus/L3/gracefo/ocean_mass/RL06/v02/GFZ//GRD-3_2018182-2018199_GRFO_GFZOP_BA01_0600_OCN_v02.nc.html",
            "Type": "VIEW RELATED INFORMATION",
            "Description": "The OPENDAP location for the granule.",
            "MimeType": "text/html"
          }
        ],
        "DataGranule": {
          "DayNightFlag": "Unspecified",
          "ProductionDateTime": "2018-07-01T00:00:00.000Z",
          "ArchiveAndDistributionInformation": [
            {
              "Name": "Not provided",
              "Size": 0.5435342788696289,
              "SizeUnit": "MB"
            }
          ]
        },
        "MetadataSpecification": {
          "URL": "https://cdn.earthdata.nasa.gov/umm/granule/v1.6",
          "Name": "UMM-G",
          "Version": "1.6"
        }
      }
    },
    {
      "meta": {
        "concept-type": "granule",
        "concept-id": "G1647446039-PODAAC",
        "revision-id": 1,
        "native-id": "GRD-3_2018295-2018313_GRFO_GFZOP_BA01_0600_OCN_v02.nc",
        "provider-id": "PODAAC",
        "format": "application/echo10+xml",
        "revision-date": "2019-10-23T19:43:02Z"
      },
      "umm": {
        "TemporalExtent": {
          "RangeDateTime": {
            "BeginningDateTime": "2018-10-22T00:00:00.000Z",
            "EndingDateTime": "2018-11-09T23:59:59.999Z"
          }
        },
        "OrbitCalculatedSpatialDomains": [
          {}
        ],
        "GranuleUR": "GRD-3_2018295-2018313_GRFO_GFZOP_BA01_0600_OCN_v02.nc",
        "SpatialExtent": {
          "HorizontalSpatialDomain": {
            "Geometry": {
              "BoundingRectangles": [
                {
                  "WestBoundingCoordinate": 0.0,
                  "EastBoundingCoordinate": 180.0,
                  "NorthBoundingCoordinate": 0.0,
                  "SouthBoundingCoordinate": 0.0
                },
                {
                  "WestBoundingCoordinate": -180.0,
                  "EastBoundingCoordinate": 0.0,
                  "NorthBoundingCoordinate": 0.0,
                  "SouthBoundingCoordinate": 0.0
                }
              ]
            }
          }
        },
        "ProviderDates": [
          {
            "Date": "2019-10-05T23:04:24.902Z",
            "Type": "Insert"
          },
          {
            "Date": "2019-10-23T19:43:01.564Z",
            "Type": "Update"
          }
        ],
        "CollectionReference": {
          "ShortName": "TELLUS_GRFO_L3_GFZ_RL06_OCN_v02",
          "Version": "RL06 v02"
        },
        "RelatedUrls": [
          {
            "URL": "https://podaac-tools.jpl.nasa.gov/drive/files/allData/tellus/L3/gracefo/ocean_mass/RL06/v02/GFZ//GRD-3_2018295-2018313_GRFO_GFZOP_BA01_0600_OCN_v02.nc",
            "Type": "GET DATA",
            "Description": "The HTTP location for the granule."
          },
          {
            "URL": "https://podaac-opendap.jpl.nasa.gov/opendap/allData/tellus/L3/gracefo/ocean_mass/RL06/v02/GFZ//GRD-3_2018295-2018313_GRFO_GFZOP_BA01_0600_OCN_v02.nc.html",
            "Type": "VIEW RELATED INFORMATION",
            "Description": "The OPENDAP location for the granule.",
            "MimeType": "text/html"
          }
        ],
        "DataGranule": {
          "DayNightFlag": "Unspecified",
          "ProductionDateTime": "2018-10-22T00:00:00.000Z",
          "ArchiveAndDistributionInformation": [
            {
              "Name": "Not provided",
              "Size": 0.5435342788696289,
              "SizeUnit": "MB"
            }
          ]
        },
        "MetadataSpecification": {
          "URL": "https://cdn.earthdata.nasa.gov/umm/granule/v1.6",
          "Name": "UMM-G",
          "Version": "1.6"
        }
      }
    },
    {
      "meta": {
        "concept-type": "granule",
        "concept-id": "G1647446043-PODAAC",
        "revision-id": 1,
        "native-id": "GRD-3_2018305-2018334_GRFO_GFZOP_BA01_0600_OCN_v02.nc",
        "provider-id": "PODAAC",
        "format": "application/echo10+xml",
        "revision-date": "2019-10-23T19:43:06Z"
      },
      "umm": {
        "TemporalExtent": {
          "RangeDateTime": {
            "BeginningDateTime": "2018-11-01T00:00:00.000Z",
            "EndingDateTime": "2018-11-30T23:59:59.999Z"
          }
        },
        "OrbitCalculatedSpatialDomains": [
          {}
        ],
        "GranuleUR": "GRD-3_2018305-2018334_GRFO_GFZOP_BA01_0600_OCN_v02.nc",
        "SpatialExtent": {
          "HorizontalSpatialDomain": {
            "Geometry": {
              "BoundingRectangles": [
                {
                  "WestBoundingCoordinate": 0.0,
                  "EastBoundingCoordinate": 180.0,
                  "NorthBoundingCoordinate": 0.0,
                  "SouthBoundingCoordinate": 0.0
                },
                {
                  "WestBoundingCoordinate": -180.0,
                  "EastBoundingCoordinate": 0.0,
                  "NorthBoundingCoordinate": 0.0,
                  "SouthBoundingCoordinate": 0.0
                }
              ]
            }
          }
        },
        "ProviderDates": [
          {
            "Date": "2019-10-05T23:04:54.425Z",
            "Type": "Insert"
          },
          {
            "Date": "2019-10-23T19:43:05.666Z",
            "Type": "Update"
          }
        ],
        "CollectionReference": {
          "ShortName": "TELLUS_GRFO_L3_GFZ_RL06_OCN_v02",
          "Version": "RL06 v02"
        },
        "RelatedUrls": [
          {
            "URL": "https://podaac-tools.jpl.nasa.gov/drive/files/allData/tellus/L3/gracefo/ocean_mass/RL06/v02/GFZ//GRD-3_2018305-2018334_GRFO_GFZOP_BA01_0600_OCN_v02.nc",
            "Type": "GET DATA",
            "Description": "The HTTP location for the granule."
          },
          {
            "URL": "https://podaac-opendap.jpl.nasa.gov/opendap/allData/tellus/L3/gracefo/ocean_mass/RL06/v02/GFZ//GRD-3_2018305-2018334_GRFO_GFZOP_BA01_0600_OCN_v02.nc.html",
            "Type": "VIEW RELATED INFORMATION",
            "Description": "The OPENDAP location for the granule.",
            "MimeType": "text/html"
          }
        ],
        "DataGranule": {
          "DayNightFlag": "Unspecified",
          "ProductionDateTime": "2018-11-01T00:00:00.000Z",
          "ArchiveAndDistributionInformation": [
            {
              "Name": "Not provided",
              "Size": 0.5435342788696289,
              "SizeUnit": "MB"
            }
          ]
        },
        "MetadataSpecification": {
          "URL": "https://cdn.earthdata.nasa.gov/umm/granule/v1.6",
          "Name": "UMM-G",
          "Version": "1.6"
        }
      }
    },
    {
      "meta": {
        "concept-type": "granule",
        "concept-id": "G1647446028-PODAAC",
        "revision-id": 1,
        "native-id": "GRD-3_2018335-2018365_GRFO_GFZOP_BA01_0600_OCN_v02.nc",
        "provider-id": "PODAAC",
        "format": "application/echo10+xml",
        "revision-date": "2019-10-23T19:42:54Z"
      },
      "umm": {
        "TemporalExtent": {
          "RangeDateTime": {
            "BeginningDateTime": "2018-12-01T00:00:00.000Z",
            "EndingDateTime": "2018-12-31T23:59:59.999Z"
          }
        },
        "OrbitCalculatedSpatialDomains": [
          {}
        ],
        "GranuleUR": "GRD-3_2018335-2018365_GRFO_GFZOP_BA01_0600_OCN_v02.nc",
        "SpatialExtent": {
          "HorizontalSpatialDomain": {
            "Geometry": {
              "BoundingRectangles": [
                {
                  "WestBoundingCoordinate": 0.0,
                  "EastBoundingCoordinate": 180.0,
                  "NorthBoundingCoordinate": 0.0,
                  "SouthBoundingCoordinate": 0.0
                },
                {
                  "WestBoundingCoordinate": -180.0,
                  "EastBoundingCoordinate": 0.0,
                  "NorthBoundingCoordinate": 0.0,
                  "SouthBoundingCoordinate": 0.0
                }
              ]
            }
          }
        },
        "ProviderDates": [
          {
            "Date": "2019-10-05T23:04:35.274Z",
            "Type": "Insert"
          },
          {
            "Date": "2019-10-23T19:42:53.330Z",
            "Type": "Update"
          }
        ],
        "CollectionReference": {
          "ShortName": "TELLUS_GRFO_L3_GFZ_RL06_OCN_v02",
          "Version": "RL06 v02"
        },
        "RelatedUrls": [
          {
            "URL": "https://podaac-tools.jpl.nasa.gov/drive/files/allData/tellus/L3/gracefo/ocean_mass/RL06/v02/GFZ//GRD-3_2018335-2018365_GRFO_GFZOP_BA01_0600_OCN_v02.nc",
            "Type": "GET DATA",
            "Description": "The HTTP location for the granule."
          },
          {
            "URL": "https://podaac-opendap.jpl.nasa.gov/opendap/allData/tellus/L3/gracefo/ocean_mass/RL06/v02/GFZ//GRD-3_2018335-2018365_GRFO_GFZOP_BA01_0600_OCN_v02.nc.html",
            "Type": "VIEW RELATED INFORMATION",
            "Description": "The OPENDAP location for the granule.",
            "MimeType": "text/html"
          }
        ],
        "DataGranule": {
          "DayNightFlag": "Unspecified",
          "ProductionDateTime": "2018-12-01T00:00:00.000Z",
          "ArchiveAndDistributionInformation": [
            {
              "Name": "Not provided",
              "Size": 0.5435342788696289,
              "SizeUnit": "MB"
            }
          ]
        },
        "MetadataSpecification": {
          "URL": "https://cdn.earthdata.nasa.gov/umm/granule/v1.6",
          "Name": "UMM-G",
          "Version": "1.6"
        }
      }
    },
    {
      "meta": {
        "concept-type": "granule",
        "concept-id": "G1647446030-PODAAC",
        "revision-id": 1,
        "native-id": "GRD-3_2019001-2019031_GRFO_GFZOP_BA01_0600_OCN_v02.nc",
        "provider-id": "PODAAC",
        "format": "application/echo10+xml",
        "revision-date": "2019-10-23T19:42:56Z"
      },
      "umm": {
        "TemporalExtent": {
          "RangeDateTime": {
            "BeginningDateTime": "2019-01-01T00:00:00.000Z",
            "EndingDateTime": "2019-01-31T23:59:59.999Z"
          }
        },
        "OrbitCalculatedSpatialDomains": [
          {}
        ],
        "GranuleUR": "GRD-3_2019001-2019031_GRFO_GFZOP_BA01_0600_OCN_v02.nc",
        "SpatialExtent": {
          "HorizontalSpatialDomain": {
            "Geometry": {
              "BoundingRectangles": [
                {
                  "WestBoundingCoordinate": 0.0,
                  "EastBoundingCoordinate": 180.0,
                  "NorthBoundingCoordinate": 0.0,
                  "SouthBoundingCoordinate": 0.0
                },
                {
                  "WestBoundingCoordinate": -180.0,
                  "EastBoundingCoordinate": 0.0,
                  "NorthBoundingCoordinate": 0.0,
                  "SouthBoundingCoordinate": 0.0
                }
              ]
            }
          }
        },
        "ProviderDates": [
          {
            "Date": "2019-10-05T23:04:03.252Z",
            "Type": "Insert"
          },
          {
            "Date": "2019-10-23T19:42:56.131Z",
            "Type": "Update"
          }
        ],
        "CollectionReference": {
          "ShortName": "TELLUS_GRFO_L3_GFZ_RL06_OCN_v02",
          "Version": "RL06 v02"
        },
        "RelatedUrls": [
          {
            "URL": "https://podaac-tools.jpl.nasa.gov/drive/files/allData/tellus/L3/gracefo/ocean_mass/RL06/v02/GFZ//GRD-3_2019001-2019031_GRFO_GFZOP_BA01_0600_OCN_v02.nc",
            "Type": "GET DATA",
            "Description": "The HTTP location for the granule."
          },
          {
            "URL": "https://podaac-opendap.jpl.nasa.gov/opendap/allData/tellus/L3/gracefo/ocean_mass/RL06/v02/GFZ//GRD-3_2019001-2019031_GRFO_GFZOP_BA01_0600_OCN_v02.nc.html",
            "Type": "VIEW RELATED INFORMATION",
            "Description": "The OPENDAP location for the granule.",
            "MimeType": "text/html"
          }
        ],
        "DataGranule": {
          "DayNightFlag": "Unspecified",
          "ProductionDateTime": "2019-01-01T00:00:00.000Z",
          "ArchiveAndDistributionInformation": [
            {
              "Name": "Not provided",
              "Size": 0.5435342788696289,
              "SizeUnit": "MB"
            }
          ]
        },
        "MetadataSpecification": {
          "URL": "https://cdn.earthdata.nasa.gov/umm/granule/v1.6",
          "Name": "UMM-G",
          "Version": "1.6"
        }
      }
    },
    {
      "meta": {
        "concept-type": "granule",
        "concept-id": "G1647446029-PODAAC",
        "revision-id": 1,
        "native-id": "GRD-3_2019026-2019063_GRFO_GFZOP_BA01_0600_OCN_v02.nc",
        "provider-id": "PODAAC",
        "format": "application/echo10+xml",
        "revision-date": "2019-10-23T19:42:55Z"
      },
      "umm": {
        "TemporalExtent": {
          "RangeDateTime": {
            "BeginningDateTime": "2019-01-26T00:00:00.000Z",
            "EndingDateTime": "2019-03-04T23:59:59.999Z"
          }
        },
        "OrbitCalculatedSpatialDomains": [
          {}
        ],
        "GranuleUR": "GRD-3_2019026-2019063_GRFO_GFZOP_BA01_0600_OCN_v02.nc",
        "SpatialExtent": {
          "HorizontalSpatialDomain": {
            "Geometry": {
              "BoundingRectangles": [
                {
                  "WestBoundingCoordinate": 0.0,
                  "EastBoundingCoordinate": 180.0,
                  "NorthBoundingCoordinate": 0.0,
                  "SouthBoundingCoordinate": 0.0
                },
                {
                  "WestBoundingCoordinate": -180.0,
                  "EastBoundingCoordinate": 0.0,
                  "NorthBoundingCoordinate": 0.0,
                  "SouthBoundingCoordinate": 0.0
                }
              ]
            }
          }
        },
        "ProviderDates": [
          {
            "Date": "2019-10-05T23:04:43.034Z",
            "Type": "Insert"
          },
          {
            "Date": "2019-10-23T19:42:54.735Z",
            "Type": "Update"
          }
        ],
        "CollectionReference": {
          "ShortName": "TELLUS_GRFO_L3_GFZ_RL06_OCN_v02",
          "Version": "RL06 v02"
        },
        "RelatedUrls": [
          {
            "URL": "https://podaac-tools.jpl.nasa.gov/drive/files/allData/tellus/L3/gracefo/ocean_mass/RL06/v02/GFZ//GRD-3_2019026-2019063_GRFO_GFZOP_BA01_0600_OCN_v02.nc",
            "Type": "GET DATA",
            "Description": "The HTTP location for the granule."
          },
          {
            "URL": "https://podaac-opendap.jpl.nasa.gov/opendap/allData/tellus/L3/gracefo/ocean_mass/RL06/v02/GFZ//GRD-3_2019026-2019063_GRFO_GFZOP_BA01_0600_OCN_v02.nc.html",
            "Type": "VIEW RELATED INFORMATION",
            "Description": "The OPENDAP location for the granule.",
            "MimeType": "text/html"
          }
        ],
        "DataGranule": {
          "DayNightFlag": "Unspecified",
          "ProductionDateTime": "2019-01-26T00:00:00.000Z",
          "ArchiveAndDistributionInformation": [
            {
              "Name": "Not provided",
              "Size": 0.5435342788696289,
              "SizeUnit": "MB"
            }
          ]
        },
        "MetadataSpecification": {
          "URL": "https://cdn.earthdata.nasa.gov/umm/granule/v1.6",
          "Name": "UMM-G",
          "Version": "1.6"
        }
      }
    },
    {
      "meta": {
        "concept-type": "granule",
        "concept-id": "G1647446035-PODAAC",
        "revision-id": 1,
        "native-id": "GRD-3_2019060-2019090_GRFO_GFZOP_BA01_0600_OCN_v02.nc",
        "provider-id": "PODAAC",
        "format": "application/echo10+xml",
        "revision-date": "2019-10-23T19:42:59Z"
      },
      "umm": {
        "TemporalExtent": {
          "RangeDateTime": {
            "BeginningDateTime": "2019-03-01T00:00:00.000Z",
            "EndingDateTime": "2019-03-31T23:59:59.999Z"
          }
        },
        "OrbitCalculatedSpatialDomains": [
          {}
        ],
        "GranuleUR": "GRD-3_2019060-2019090_GRFO_GFZOP_BA01_0600_OCN_v02.nc",
        "SpatialExtent": {
          "HorizontalSpatialDomain": {
            "Geometry": {
              "BoundingRectangles": [
                {
                  "WestBoundingCoordinate": 0.0,
                  "EastBoundingCoordinate": 180.0,
                  "NorthBoundingCoordinate": 0.0,
                  "SouthBoundingCoordinate": 0.0
                },
                {
                  "WestBoundingCoordinate": -180.0,
                  "EastBoundingCoordinate": 0.0,
                  "NorthBoundingCoordinate": 0.0,
                  "SouthBoundingCoordinate": 0.0
                }
              ]
            }
          }
        },
        "ProviderDates": [
          {
            "Date": "2019-10-05T23:03:54.878Z",
            "Type": "Insert"
          },
          {
            "Date": "2019-10-23T19:42:58.819Z",
            "Type": "Update"
          }
        ],
        "CollectionReference": {
          "ShortName": "TELLUS_GRFO_L3_GFZ_RL06_OCN_v02",
          "Version": "RL06 v02"
        },
        "RelatedUrls": [
          {
            "URL": "https://podaac-tools.jpl.nasa.gov/drive/files/allData/tellus/L3/gracefo/ocean_mass/RL06/v02/GFZ//GRD-3_2019060-2019090_GRFO_GFZOP_BA01_0600_OCN_v02.nc",
            "Type": "GET DATA",
            "Description": "The HTTP location for the granule."
          },
          {
            "URL": "https://podaac-opendap.jpl.nasa.gov/opendap/allData/tellus/L3/gracefo/ocean_mass/RL06/v02/GFZ//GRD-3_2019060-2019090_GRFO_GFZOP_BA01_0600_OCN_v02.nc.html",
            "Type": "VIEW RELATED INFORMATION",
            "Description": "The OPENDAP location for the granule.",
            "MimeType": "text/html"
          }
        ],
        "DataGranule": {
          "DayNightFlag": "Unspecified",
          "ProductionDateTime": "2019-03-01T00:00:00.000Z",
          "ArchiveAndDistributionInformation": [
            {
              "Name": "Not provided",
              "Size": 0.5435342788696289,
              "SizeUnit": "MB"
            }
          ]
        },
        "MetadataSpecification": {
          "URL": "https://cdn.earthdata.nasa.gov/umm/granule/v1.6",
          "Name": "UMM-G",
          "Version": "1.6"
        }
      }
    },
    {
      "meta": {
        "concept-type": "granule",
        "concept-id": "G1647446042-PODAAC",
        "revision-id": 1,
        "native-id": "GRD-3_2019091-2019120_GRFO_GFZOP_BA01_0600_OCN_v02.nc",
        "provider-id": "PODAAC",
        "format": "application/echo10+xml",
        "revision-date": "2019-10-23T19:43:05Z"
      },
      "umm": {
        "TemporalExtent": {
          "RangeDateTime": {
            "BeginningDateTime": "2019-04-01T00:00:00.000Z",
            "EndingDateTime": "2019-04-30T23:59:59.999Z"
          }
        },
        "OrbitCalculatedSpatialDomains": [
          {}
        ],
        "GranuleUR": "GRD-3_2019091-2019120_GRFO_GFZOP_BA01_0600_OCN_v02.nc",
        "SpatialExtent": {
          "HorizontalSpatialDomain": {
            "Geometry": {
              "BoundingRectangles": [
                {
                  "WestBoundingCoordinate": 0.0,
                  "EastBoundingCoordinate": 180.0,
                  "NorthBoundingCoordinate": 0.0,
                  "SouthBoundingCoordinate": 0.0
                },
                {
                  "WestBoundingCoordinate": -180.0,
                  "EastBoundingCoordinate": 0.0,
                  "NorthBoundingCoordinate": 0.0,
                  "SouthBoundingCoordinate": 0.0
                }
              ]
            }
          }
        },
        "ProviderDates": [
          {
            "Date": "2019-10-05T23:04:48.077Z",
            "Type": "Insert"
          },
          {
            "Date": "2019-10-23T19:43:04.364Z",
            "Type": "Update"
          }
        ],
        "CollectionReference": {
          "ShortName": "TELLUS_GRFO_L3_GFZ_RL06_OCN_v02",
          "Version": "RL06 v02"
        },
        "RelatedUrls": [
          {
            "URL": "https://podaac-tools.jpl.nasa.gov/drive/files/allData/tellus/L3/gracefo/ocean_mass/RL06/v02/GFZ//GRD-3_2019091-2019120_GRFO_GFZOP_BA01_0600_OCN_v02.nc",
            "Type": "GET DATA",
            "Description": "The HTTP location for the granule."
          },
          {
            "URL": "https://podaac-opendap.jpl.nasa.gov/opendap/allData/tellus/L3/gracefo/ocean_mass/RL06/v02/GFZ//GRD-3_2019091-2019120_GRFO_GFZOP_BA01_0600_OCN_v02.nc.html",
            "Type": "VIEW RELATED INFORMATION",
            "Description": "The OPENDAP location for the granule.",
            "MimeType": "text/html"
          }
        ],
        "DataGranule": {
          "DayNightFlag": "Unspecified",
          "ProductionDateTime": "2019-04-01T00:00:00.000Z",
          "ArchiveAndDistributionInformation": [
            {
              "Name": "Not provided",
              "Size": 0.5435342788696289,
              "SizeUnit": "MB"
            }
          ]
        },
        "MetadataSpecification": {
          "URL": "https://cdn.earthdata.nasa.gov/umm/granule/v1.6",
          "Name": "UMM-G",
          "Version": "1.6"
        }
      }
    },
    {
      "meta": {
        "concept-type": "granule",
        "concept-id": "G1647446041-PODAAC",
        "revision-id": 1,
        "native-id": "GRD-3_2019121-2019151_GRFO_GFZOP_BA01_0600_OCN_v02.nc",
        "provider-id": "PODAAC",
        "format": "application/echo10+xml",
        "revision-date": "2019-10-23T19:43:03Z"
      },
      "umm": {
        "TemporalExtent": {
          "RangeDateTime": {
            "BeginningDateTime": "2019-05-01T00:00:00.000Z",
            "EndingDateTime": "2019-05-31T23:59:59.999Z"
          }
        },
        "OrbitCalculatedSpatialDomains": [
          {}
        ],
        "GranuleUR": "GRD-3_2019121-2019151_GRFO_GFZOP_BA01_0600_OCN_v02.nc",
        "SpatialExtent": {
          "HorizontalSpatialDomain": {
            "Geometry": {
              "BoundingRectangles": [
                {
                  "WestBoundingCoordinate": 0.0,
                  "EastBoundingCoordinate": 180.0,
                  "NorthBoundingCoordinate": 0.0,
                  "SouthBoundingCoordinate": 0.0
                },
                {
                  "WestBoundingCoordinate": -180.0,
                  "EastBoundingCoordinate": 0.0,
                  "NorthBoundingCoordinate": 0.0,
                  "SouthBoundingCoordinate": 0.0
                }
              ]
            }
          }
        },
        "ProviderDates": [
          {
            "Date": "2019-10-05T23:04:19.457Z",
            "Type": "Insert"
          },
          {
            "Date": "2019-10-23T19:43:03.005Z",
            "Type": "Update"
          }
        ],
        "CollectionReference": {
          "ShortName": "TELLUS_GRFO_L3_GFZ_RL06_OCN_v02",
          "Version": "RL06 v02"
        },
        "RelatedUrls": [
          {
            "URL": "https://podaac-tools.jpl.nasa.gov/drive/files/allData/tellus/L3/gracefo/ocean_mass/RL06/v02/GFZ//GRD-3_2019121-2019151_GRFO_GFZOP_BA01_0600_OCN_v02.nc",
            "Type": "GET DATA",
            "Description": "The HTTP location for the granule."
          },
          {
            "URL": "https://podaac-opendap.jpl.nasa.gov/opendap/allData/tellus/L3/gracefo/ocean_mass/RL06/v02/GFZ//GRD-3_2019121-2019151_GRFO_GFZOP_BA01_0600_OCN_v02.nc.html",
            "Type": "VIEW RELATED INFORMATION",
            "Description": "The OPENDAP location for the granule.",
            "MimeType": "text/html"
          }
        ],
        "DataGranule": {
          "DayNightFlag": "Unspecified",
          "ProductionDateTime": "2019-05-01T00:00:00.000Z",
          "ArchiveAndDistributionInformation": [
            {
              "Name": "Not provided",
              "Size": 0.5435342788696289,
              "SizeUnit": "MB"
            }
          ]
        },
        "MetadataSpecification": {
          "URL": "https://cdn.earthdata.nasa.gov/umm/granule/v1.6",
          "Name": "UMM-G",
          "Version": "1.6"
        }
      }
    },
    {
      "meta": {
        "concept-type": "granule",
        "concept-id": "G1647446027-PODAAC",
        "revision-id": 1,
        "native-id": "GRD-3_2019152-2019181_GRFO_GFZOP_BA01_0600_OCN_v02.nc",
        "provider-id": "PODAAC",
        "format": "application/echo10+xml",
        "revision-date": "2019-10-23T19:42:52Z"
      },
      "umm": {
        "TemporalExtent": {
          "RangeDateTime": {
            "BeginningDateTime": "2019-06-01T00:00:00.000Z",
            "EndingDateTime": "2019-06-30T23:59:59.999Z"
          }
        },
        "OrbitCalculatedSpatialDomains": [
          {}
        ],
        "GranuleUR": "GRD-3_2019152-2019181_GRFO_GFZOP_BA01_0600_OCN_v02.nc",
        "SpatialExtent": {
          "HorizontalSpatialDomain": {
            "Geometry": {
              "BoundingRectangles": [
                {
                  "WestBoundingCoordinate": 0.0,
                  "EastBoundingCoordinate": 180.0,
                  "NorthBoundingCoordinate": 0.0,
                  "SouthBoundingCoordinate": 0.0
                },
                {
                  "WestBoundingCoordinate": -180.0,
                  "EastBoundingCoordinate": 0.0,
                  "NorthBoundingCoordinate": 0.0,
                  "SouthBoundingCoordinate": 0.0
                }
              ]
            }
          }
        },
        "ProviderDates": [
          {
            "Date": "2019-10-05T23:04:29.497Z",
            "Type": "Insert"
          },
          {
            "Date": "2019-10-23T19:42:51.912Z",
            "Type": "Update"
          }
        ],
        "CollectionReference": {
          "ShortName": "TELLUS_GRFO_L3_GFZ_RL06_OCN_v02",
          "Version": "RL06 v02"
        },
        "RelatedUrls": [
          {
            "URL": "https://podaac-tools.jpl.nasa.gov/drive/files/allData/tellus/L3/gracefo/ocean_mass/RL06/v02/GFZ//GRD-3_2019152-2019181_GRFO_GFZOP_BA01_0600_OCN_v02.nc",
            "Type": "GET DATA",
            "Description": "The HTTP location for the granule."
          },
          {
            "URL": "https://podaac-opendap.jpl.nasa.gov/opendap/allData/tellus/L3/gracefo/ocean_mass/RL06/v02/GFZ//GRD-3_2019152-2019181_GRFO_GFZOP_BA01_0600_OCN_v02.nc.html",
            "Type": "VIEW RELATED INFORMATION",
            "Description": "The OPENDAP location for the granule.",
            "MimeType": "text/html"
          }
        ],
        "DataGranule": {
          "DayNightFlag": "Unspecified",
          "ProductionDateTime": "2019-06-01T00:00:00.000Z",
          "ArchiveAndDistributionInformation": [
            {
              "Name": "Not provided",
              "Size": 0.5435342788696289,
              "SizeUnit": "MB"
            }
          ]
        },
        "MetadataSpecification": {
          "URL": "https://cdn.earthdata.nasa.gov/umm/granule/v1.6",
          "Name": "UMM-G",
          "Version": "1.6"
        }
      }
    },
    {
      "meta": {
        "concept-type": "granule",
        "concept-id": "G1647446026-PODAAC",
        "revision-id": 1,
        "native-id": "GRD-3_2019182-2019212_GRFO_GFZOP_BA01_0600_OCN_v02.nc",
        "provider-id": "PODAAC",
        "format": "application/echo10+xml",
        "revision-date": "2019-10-23T19:42:51Z"
      },
      "umm": {
        "TemporalExtent": {
          "RangeDateTime": {
            "BeginningDateTime": "2019-07-01T00:00:00.000Z",
            "EndingDateTime": "2019-07-31T23:59:59.999Z"
          }
        },
        "OrbitCalculatedSpatialDomains": [
          {}
        ],
        "GranuleUR": "GRD-3_2019182-2019212_GRFO_GFZOP_BA01_0600_OCN_v02.nc",
        "SpatialExtent": {
          "HorizontalSpatialDomain": {
            "Geometry": {
              "BoundingRectangles": [
                {
                  "WestBoundingCoordinate": 0.0,
                  "EastBoundingCoordinate": 180.0,
                  "NorthBoundingCoordinate": 0.0,
                  "SouthBoundingCoordinate": 0.0
                },
                {
                  "WestBoundingCoordinate": -180.0,
                  "EastBoundingCoordinate": 0.0,
                  "NorthBoundingCoordinate": 0.0,
                  "SouthBoundingCoordinate": 0.0
                }
              ]
            }
          }
        },
        "ProviderDates": [
          {
            "Date": "2019-10-05T23:04:09.365Z",
            "Type": "Insert"
          },
          {
            "Date": "2019-10-23T19:42:48.764Z",
            "Type": "Update"
          }
        ],
        "CollectionReference": {
          "ShortName": "TELLUS_GRFO_L3_GFZ_RL06_OCN_v02",
          "Version": "RL06 v02"
        },
        "RelatedUrls": [
          {
            "URL": "https://podaac-tools.jpl.nasa.gov/drive/files/allData/tellus/L3/gracefo/ocean_mass/RL06/v02/GFZ//GRD-3_2019182-2019212_GRFO_GFZOP_BA01_0600_OCN_v02.nc",
            "Type": "GET DATA",
            "Description": "The HTTP location for the granule."
          },
          {
            "URL": "https://podaac-opendap.jpl.nasa.gov/opendap/allData/tellus/L3/gracefo/ocean_mass/RL06/v02/GFZ//GRD-3_2019182-2019212_GRFO_GFZOP_BA01_0600_OCN_v02.nc.html",
            "Type": "VIEW RELATED INFORMATION",
            "Description": "The OPENDAP location for the granule.",
            "MimeType": "text/html"
          }
        ],
        "DataGranule": {
          "DayNightFlag": "Unspecified",
          "ProductionDateTime": "2019-07-01T00:00:00.000Z",
          "ArchiveAndDistributionInformation": [
            {
              "Name": "Not provided",
              "Size": 0.5435342788696289,
              "SizeUnit": "MB"
            }
          ]
        },
        "MetadataSpecification": {
          "URL": "https://cdn.earthdata.nasa.gov/umm/granule/v1.6",
          "Name": "UMM-G",
          "Version": "1.6"
        }
      }
    },
    {
      "meta": {
        "concept-type": "granule",
        "concept-id": "G1649939485-PODAAC",
        "revision-id": 2,
        "native-id": "GRD-3_2019213-2019243_GRFO_GFZOP_BA01_0600_OCN_v02.nc",
        "provider-id": "PODAAC",
        "format": "application/echo10+xml",
        "revision-date": "2019-11-01T12:50:31Z"
      },
      "umm": {
        "TemporalExtent": {
          "RangeDateTime": {
            "BeginningDateTime": "2019-08-01T00:00:00.000Z",
            "EndingDateTime": "2019-08-31T23:59:59.999Z"
          }
        },
        "OrbitCalculatedSpatialDomains": [
          {}
        ],
        "GranuleUR": "GRD-3_2019213-2019243_GRFO_GFZOP_BA01_0600_OCN_v02.nc",
        "SpatialExtent": {
          "HorizontalSpatialDomain": {
            "Geometry": {
              "BoundingRectangles": [
                {
                  "WestBoundingCoordinate": 0.0,
                  "EastBoundingCoordinate": 180.0,
                  "NorthBoundingCoordinate": 0.0,
                  "SouthBoundingCoordinate": 0.0
                },
                {
                  "WestBoundingCoordinate": -180.0,
                  "EastBoundingCoordinate": 0.0,
                  "NorthBoundingCoordinate": 0.0,
                  "SouthBoundingCoordinate": 0.0
                }
              ]
            }
          }
        },
        "ProviderDates": [
          {
            "Date": "2019-10-31T06:28:00.737Z",
            "Type": "Insert"
          },
          {
            "Date": "2019-11-01T12:50:29.320Z",
            "Type": "Update"
          }
        ],
        "CollectionReference": {
          "ShortName": "TELLUS_GRFO_L3_GFZ_RL06_OCN_v02",
          "Version": "RL06 v02"
        },
        "RelatedUrls": [
          {
            "URL": "https://podaac-tools.jpl.nasa.gov/drive/files/allData/tellus/L3/gracefo/ocean_mass/RL06/v02/GFZ//GRD-3_2019213-2019243_GRFO_GFZOP_BA01_0600_OCN_v02.nc",
            "Type": "GET DATA",
            "Description": "The HTTP location for the granule."
          },
          {
            "URL": "https://podaac-opendap.jpl.nasa.gov/opendap/allData/tellus/L3/gracefo/ocean_mass/RL06/v02/GFZ//GRD-3_2019213-2019243_GRFO_GFZOP_BA01_0600_OCN_v02.nc.html",
            "Type": "VIEW RELATED INFORMATION",
            "Description": "The OPENDAP location for the granule.",
            "MimeType": "text/html"
          }
        ],
        "DataGranule": {
          "DayNightFlag": "Unspecified",
          "ProductionDateTime": "2019-08-01T00:00:00.000Z",
          "ArchiveAndDistributionInformation": [
            {
              "Name": "Not provided",
              "Size": 0.5435314178466797,
              "SizeUnit": "MB"
            }
          ]
        },
        "MetadataSpecification": {
          "URL": "https://cdn.earthdata.nasa.gov/umm/granule/v1.6",
          "Name": "UMM-G",
          "Version": "1.6"
        }
      }
    },
    {
      "meta": {
        "concept-type": "granule",
        "concept-id": "G1654246717-PODAAC",
        "revision-id": 2,
        "native-id": "GRD-3_2019244-2019273_GRFO_GFZOP_BA01_0600_OCN_v02.nc",
        "provider-id": "PODAAC",
        "format": "application/echo10+xml",
        "revision-date": "2019-11-10T12:56:23Z"
      },
      "umm": {
        "TemporalExtent": {
          "RangeDateTime": {
            "BeginningDateTime": "2019-09-01T00:00:00.000Z",
            "EndingDateTime": "2019-09-30T23:59:59.999Z"
          }
        },
        "OrbitCalculatedSpatialDomains": [
          {}
        ],
        "GranuleUR": "GRD-3_2019244-2019273_GRFO_GFZOP_BA01_0600_OCN_v02.nc",
        "SpatialExtent": {
          "HorizontalSpatialDomain": {
            "Geometry": {
              "BoundingRectangles": [
                {
                  "WestBoundingCoordinate": 0.0,
                  "EastBoundingCoordinate": 180.0,
                  "NorthBoundingCoordinate": 0.0,
                  "SouthBoundingCoordinate": 0.0
                },
                {
                  "WestBoundingCoordinate": -180.0,
                  "EastBoundingCoordinate": 0.0,
                  "NorthBoundingCoordinate": 0.0,
                  "SouthBoundingCoordinate": 0.0
                }
              ]
            }
          }
        },
        "ProviderDates": [
          {
            "Date": "2019-11-09T05:41:24.329Z",
            "Type": "Insert"
          },
          {
            "Date": "2019-11-10T12:56:21.030Z",
            "Type": "Update"
          }
        ],
        "CollectionReference": {
          "ShortName": "TELLUS_GRFO_L3_GFZ_RL06_OCN_v02",
          "Version": "RL06 v02"
        },
        "RelatedUrls": [
          {
            "URL": "https://podaac-tools.jpl.nasa.gov/drive/files/allData/tellus/L3/gracefo/ocean_mass/RL06/v02/GFZ//GRD-3_2019244-2019273_GRFO_GFZOP_BA01_0600_OCN_v02.nc",
            "Type": "GET DATA",
            "Description": "The HTTP location for the granule."
          },
          {
            "URL": "https://podaac-opendap.jpl.nasa.gov/opendap/allData/tellus/L3/gracefo/ocean_mass/RL06/v02/GFZ//GRD-3_2019244-2019273_GRFO_GFZOP_BA01_0600_OCN_v02.nc.html",
            "Type": "VIEW RELATED INFORMATION",
            "Description": "The OPENDAP location for the granule.",
            "MimeType": "text/html"
          }
        ],
        "DataGranule": {
          "DayNightFlag": "Unspecified",
          "ProductionDateTime": "2019-09-01T00:00:00.000Z",
          "ArchiveAndDistributionInformation": [
            {
              "Name": "Not provided",
              "Size": 0.5435314178466797,
              "SizeUnit": "MB"
            }
          ]
        },
        "MetadataSpecification": {
          "URL": "https://cdn.earthdata.nasa.gov/umm/granule/v1.6",
          "Name": "UMM-G",
          "Version": "1.6"
        }
      }
    }
  ]
}