{
  "hits": 17,
  "took": 27,
  "items": [
    {
      "meta": {
        "concept-type": "granule",
        "concept-id": "G1633357976-ORNL_DAAC",
        "revision-id": 1,
        "native-id": "CMS_Forest_Carbon_Stocks.forest_group_NAFD.tif",
        "provider-id": "ORNL_DAAC",
        "format": "application/echo10+xml",
        "revision-date": "2019-09-13T13:33:26Z"
      },
      "umm": {
        "TemporalExtent": {
          "RangeDateTime": {
            "BeginningDateTime": "1986-01-01T00:00:00.000Z",
            "EndingDateTime": "2010-12-31T00:00:00.000Z"
          }
        },
        "GranuleUR": "CMS_Forest_Carbon_Stocks.forest_group_NAFD.tif",
        "MeasuredParameters": [
          {
            "ParameterName": "FORESTS"
          },
          {
            "ParameterName": "CARBON"
          },
          {
            "ParameterName": "LAND USE CLASSES"
          },
          {
            "ParameterName": "BIOMASS"
          }
        ],
        "SpatialExtent": {
          "HorizontalSpatialDomain": {
            "Geometry": {
              "BoundingRectangles": [
                {
                  "WestBoundingCoordinate": -89.0103,
                  "EastBoundingCoordinate": -71.2798,
                  "NorthBoundingCoordinate": 40.8894,
                  "SouthBoundingCoordinate": 23.2283
                }
              ]
            }
          }
        },
        "ProviderDates": [
          {
            "Date": "2019-09-12T00:00:00.000Z",
            "Type": "Insert"
          },
          {
            "Date": "2019-09-13T13:33:23.000Z",
            "Type": "Update"
          }
        ],
        "CollectionReference": {
          "ShortName": "CMS_Forest_Carbon_Stocks_1728",
          "Version": "1"
        },
        "RelatedUrls": [
          {
            "URL": "https://daac.ornl.gov/daacdata/cms/CMS_Forest_Carbon_Stocks/data/forest_group_NAFD.tif",
            "Type": "GET DATA",
            "Description": "This link provides direct download access to the granule."
          },
          {
            "URL": "https://daac.ornl.gov/CMS/guides/CMS_Forest_Carbon_Stocks.html",
            "Type": "VIEW RELATED INFORMATION",
            "Description": "ORNL DAAC Data Set Documentation"
          },
          {
            "URL": "https://dx.doi.org/10.3334/ORNLDAAC/1728",
            "Type": "VIEW RELATED INFORMATION",
            "Description": "Data set Landing Page DOI URL"
          },
          {
            "URL": "https:/daac.ornl.gov/daacdata/cms/CMS_Forest_Carbon_Stocks/comp/CMS_Forest_Carbon_Stocks.pdf",
            "Type": "VIEW RELATED INFORMATION",
            "Description": "Data Set Documentation"
          }
        ],
        "Projects": [
          {
            "ShortName": "Not provided",
            "Campaigns": [
              "CMS"
            ]
          }
        ],
        "DataGranule": {
          "DayNightFlag": "Both",
          "ProductionDateTime": "2019-09-12T00:00:00.000Z",
          "ArchiveAndDistributionInformation": [
            {
              "Name": "Not provided",
              "Size": 205.955459,
              "SizeUnit": "NA"
            }
          ]
        },
        "Platforms": [
          {
            "ShortName": "Environmental Modeling",
            "Instruments": [
              {
                "ShortName": "Computer"
              }
            ]
          }
        ]
      }
    },
    {
      "meta": {
        "concept-type": "granule",
        "concept-id": "G1633357979-ORNL_DAAC",
        "revision-id": 1,
        "native-id": "CMS_Forest_Carbon_Stocks.type_cover_years_disturb_NAFD.tif",
        "provider-id": "ORNL_DAAC",
        "format": "application/echo10+xml",
        "revision-date": "2019-09-13T13:33:26Z"
      },
      "umm": {
        "TemporalExtent": {
          "RangeDateTime": {
            "BeginningDateTime": "1986-01-01T00:00:00.000Z",
            "EndingDateTime": "2010-12-31T00:00:00.000Z"
          }
        },
        "GranuleUR": "CMS_Forest_Carbon_Stocks.type_cover_years_disturb_NAFD.tif",
        "MeasuredParameters": [
          {
            "ParameterName": "FORESTS"
          },
          {
            "ParameterName": "CARBON"
          },
          {
            "ParameterName": "LAND USE CLASSES"
          },
          {
            "ParameterName": "BIOMASS"
          }
        ],
        "SpatialExtent": {
          "HorizontalSpatialDomain": {
            "Geometry": {
              "BoundingRectangles": [
                {
                  "WestBoundingCoordinate": -89.0103,
                  "EastBoundingCoordinate": -71.2798,
                  "NorthBoundingCoordinate": 40.8894,
                  "SouthBoundingCoordinate": 23.2283
                }
              ]
            }
          }
        },
        "ProviderDates": [
          {
            "Date": "2019-09-12T00:00:00.000Z",
            "Type": "Insert"
          },
          {
            "Date": "2019-09-13T13:33:23.000Z",
            "Type": "Update"
          }
        ],
        "CollectionReference": {
          "ShortName": "CMS_Forest_Carbon_Stocks_1728",
          "Version": "1"
        },
        "RelatedUrls": [
          {
            "URL": "https://daac.ornl.gov/daacdata/cms/CMS_Forest_Carbon_Stocks/data/type_cover_years_disturb_NAFD.tif",
            "Type": "GET DATA",
            "Description": "This link provides direct download access to the granule."
          },
          {
            "URL": "https://daac.ornl.gov/CMS/guides/CMS_Forest_Carbon_Stocks.html",
            "Type": "VIEW RELATED INFORMATION",
            "Description": "ORNL DAAC Data Set Documentation"
          },
          {
            "URL": "https://dx.doi.org/10.3334/ORNLDAAC/1728",
            "Type": "VIEW RELATED INFORMATION",
            "Description": "Data set Landing Page DOI URL"
          },
          {
            "URL": "https:/daac.ornl.gov/daacdata/cms/CMS_Forest_Carbon_Stocks/comp/CMS_Forest_Carbon_Stocks.pdf",
            "Type": "VIEW RELATED INFORMATION",
            "Description": "Data Set Documentation"
          }
        ],
        "Projects": [
          {
            "ShortName": "Not provided",
            "Campaigns": [
              "CMS"
            ]
          }
        ],
        "DataGranule": {
          "DayNightFlag": "Both",
          "ProductionDateTime": "2019-09-12T00:00:00.000Z",
          "ArchiveAndDistributionInformation": [
            {
              "Name": "Not provided",
              "Size": 264.037964,
              "SizeUnit": "NA"
            }
          ]
        },
        "Platforms": [
          {
            "ShortName": "Environmental Modeling",
            "Instruments": [
              {
                "ShortName": "Computer"
              }
            ]
          }
        ]
      }
    },
    {
      "meta": {
        "concept-type": "granule",
        "concept-id": "G1633357980-ORNL_DAAC",
        "revision-id": 1,
        "native-id": "CMS_Forest_Carbon_Stocks.type_disturb_composite.tif",
        "provider-id": "ORNL_DAAC",
        "format": "application/echo10+xml",
        "revision-date": "2019-09-13T13:33:26Z"
      },
      "umm": {
        "TemporalExtent": {
          "RangeDateTime": {
            "BeginningDateTime": "1986-01-01T00:00:00.000Z",
            "EndingDateTime": "2010-12-31T00:00:00.000Z"
          }
        },
        "GranuleUR": "CMS_Forest_Carbon_Stocks.type_disturb_composite.tif",
        "MeasuredParameters": [
          {
            "ParameterName": "FORESTS"
          },
          {
            "ParameterName": "CARBON"
          },
          {
            "ParameterName": "LAND USE CLASSES"
          },
          {
            "ParameterName": "BIOMASS"
          }
        ],
        "SpatialExtent": {
          "HorizontalSpatialDomain": {
            "Geometry": {
              "BoundingRectangles": [
                {
                  "WestBoundingCoordinate": -89.0103,
                  "EastBoundingCoordinate": -71.2798,
                  "NorthBoundingCoordinate": 40.8894,
                  "SouthBoundingCoordinate": 23.2283
                }
              ]
            }
          }
        },
        "ProviderDates": [
          {
            "Date": "2019-09-12T00:00:00.000Z",
            "Type": "Insert"
          },
          {
            "Date": "2019-09-13T13:33:23.000Z",
            "Type": "Update"
          }
        ],
        "CollectionReference": {
          "ShortName": "CMS_Forest_Carbon_Stocks_1728",
          "Version": "1"
        },
        "RelatedUrls": [
          {
            "URL": "https://daac.ornl.gov/daacdata/cms/CMS_Forest_Carbon_Stocks/data/type_disturb_composite.tif",
            "Type": "GET DATA",
            "Description": "This link provides direct download access to the granule."
          },
          {
            "URL": "https://daac.ornl.gov/CMS/guides/CMS_Forest_Carbon_Stocks.html",
            "Type": "VIEW RELATED INFORMATION",
            "Description": "ORNL DAAC Data Set Documentation"
          },
          {
            "URL": "https://dx.doi.org/10.3334/ORNLDAAC/1728",
            "Type": "VIEW RELATED INFORMATION",
            "Description": "Data set Landing Page DOI URL"
          },
          {
            "URL": "https:/daac.ornl.gov/daacdata/cms/CMS_Forest_Carbon_Stocks/comp/CMS_Forest_Carbon_Stocks.pdf",
            "Type": "VIEW RELATED INFORMATION",
            "Description": "Data Set Documentation"
          }
        ],
        "Projects": [
          {
            "ShortName": "Not provided",
            "Campaigns": [
              "CMS"
            ]
          }
        ],
        "DataGranule": {
          "DayNightFlag": "Both",
          "ProductionDateTime": "2019-09-12T00:00:00.000Z",
          "ArchiveAndDistributionInformation": [
            {
              "Name": "Not provided",
              "Size": 111.880725,
              "SizeUnit": "NA"
            }
          ]
        },
        "Platforms": [
          {
            "ShortName": "Environmental Modeling",
            "Instruments": [
              {
                "ShortName": "Computer"
              }
            ]
          }
        ]
      }
    },
    {
      "meta": {
        "concept-type": "granule",
        "concept-id": "G1633357984-ORNL_DAAC",
        "revision-id": 1,
        "native-id": "CMS_Forest_Carbon_Stocks.years_disturb_ADS.tif",
        "provider-id": "ORNL_DAAC",
        "format": "application/echo10+xml",
        "revision-date": "2019-09-13T13:33:26Z"
      },
      "umm": {
        "TemporalExtent": {
          "RangeDateTime": {
            "BeginningDateTime": "1986-01-01T00:00:00.000Z",
            "EndingDateTime": "2010-12-31T00:00:00.000Z"
          }
        },
        "GranuleUR": "CMS_Forest_Carbon_Stocks.years_disturb_ADS.tif",
        "MeasuredParameters": [
          {
            "ParameterName": "FORESTS"
          },
          {
            "ParameterName": "CARBON"
          },
          {
            "ParameterName": "LAND USE CLASSES"
          },
          {
            "ParameterName": "BIOMASS"
          }
        ],
        "SpatialExtent": {
          "HorizontalSpatialDomain": {
            "Geometry": {
              "BoundingRectangles": [
                {
                  "WestBoundingCoordinate": -89.0103,
                  "EastBoundingCoordinate": -71.2798,
                  "NorthBoundingCoordinate": 40.8894,
                  "SouthBoundingCoordinate": 23.2283
                }
              ]
            }
          }
        },
        "ProviderDates": [
          {
            "Date": "2019-09-12T00:00:00.000Z",
            "Type": "Insert"
          },
          {
            "Date": "2019-09-13T13:33:23.000Z",
            "Type": "Update"
          }
        ],
        "CollectionReference": {
          "ShortName": "CMS_Forest_Carbon_Stocks_1728",
          "Version": "1"
        },
        "RelatedUrls": [
          {
            "URL": "https://daac.ornl.gov/daacdata/cms/CMS_Forest_Carbon_Stocks/data/years_disturb_ADS.tif",
            "Type": "GET DATA",
            "Description": "This link provides direct download access to the granule."
          },
          {
            "URL": "https://daac.ornl.gov/CMS/guides/CMS_Forest_Carbon_Stocks.html",
            "Type": "VIEW RELATED INFORMATION",
            "Description": "ORNL DAAC Data Set Documentation"
          },
          {
            "URL": "https://dx.doi.org/10.3334/ORNLDAAC/1728",
            "Type": "VIEW RELATED INFORMATION",
            "Description": "Data set Landing Page DOI URL"
          },
          {
            "URL": "https:/daac.ornl.gov/daacdata/cms/CMS_Forest_Carbon_Stocks/comp/CMS_Forest_Carbon_Stocks.pdf",
            "Type": "VIEW RELATED INFORMATION",
            "Description": "Data Set Documentation"
          }
        ],
        "Projects": [
          {
            "ShortName": "Not provided",
            "Campaigns": [
              "CMS"
            ]
          }
        ],
        "DataGranule": {
          "DayNightFlag": "Both",
          "ProductionDateTime": "2019-09-12T00:00:00.000Z",
          "ArchiveAndDistributionInformation": [
            {
              "Name": "Not provided",
              "Size": 33.388798,
              "SizeUnit": "NA"
            }
          ]
        },
        "Platforms": [
          {
            "ShortName": "Environmental Modeling",
            "Instruments": [
              {
                "ShortName": "Computer"
              }
            ]
          }
        ]
      }
    },
    {
      "meta": {
        "concept-type": "granule",
        "concept-id": "G1633357985-ORNL_DAAC",
        "revision-id": 1,
        "native-id": "CMS_Forest_Carbon_Stocks.years_disturb_MTBS.tif",
        "provider-id": "ORNL_DAAC",
        "format": "application/echo10+xml",
        "revision-date": "2019-09-13T13:33:26Z"
      },
      "umm": {
        "TemporalExtent": {
          "RangeDateTime": {
            "BeginningDateTime": "1986-01-01T00:00:00.000Z",
            "EndingDateTime": "2010-12-31T00:00:00.000Z"
          }
        },
        "GranuleUR": "CMS_Forest_Carbon_Stocks.years_disturb_MTBS.tif",
        "MeasuredParameters": [
          {
            "ParameterName": "FORESTS"
          },
          {
            "ParameterName": "CARBON"
          },
          {
            "ParameterName": "LAND USE CLASSES"
          },
          {
            "ParameterName": "BIOMASS"
          }
        ],
        "SpatialExtent": {
          "HorizontalSpatialDomain": {
            "Geometry": {
              "BoundingRectangles": [
                {
                  "WestBoundingCoordinate": -88.9343,
                  "EastBoundingCoordinate": -71.2798,
                  "NorthBoundingCoordinate": 40.8894,
                  "SouthBoundingCoordinate": 24.165
                }
              ]
            }
          }
        },
        "ProviderDates": [
          {
            "Date": "2019-09-12T00:00:00.000Z",
            "Type": "Insert"
          },
          {
            "Date": "2019-09-13T13:33:23.000Z",
            "Type": "Update"
          }
        ],
        "CollectionReference": {
          "ShortName": "CMS_Forest_Carbon_Stocks_1728",
          "Version": "1"
        },
        "RelatedUrls": [
          {
            "URL": "https://daac.ornl.gov/daacdata/cms/CMS_Forest_Carbon_Stocks/data/years_disturb_MTBS.tif",
            "Type": "GET DATA",
            "Description": "This link provides direct download access to the granule."
          },
          {
            "URL": "https://daac.ornl.gov/CMS/guides/CMS_Forest_Carbon_Stocks.html",
            "Type": "VIEW RELATED INFORMATION",
            "Description": "ORNL DAAC Data Set Documentation"
          },
          {
            "URL": "https://dx.doi.org/10.3334/ORNLDAAC/1728",
            "Type": "VIEW RELATED INFORMATION",
            "Description": "Data set Landing Page DOI URL"
          },
          {
            "URL": "https:/daac.ornl.gov/daacdata/cms/CMS_Forest_Carbon_Stocks/comp/CMS_Forest_Carbon_Stocks.pdf",
            "Type": "VIEW RELATED INFORMATION",
            "Description": "Data Set Documentation"
          }
        ],
        "Projects": [
          {
            "ShortName": "Not provided",
            "Campaigns": [
              "CMS"
            ]
          }
        ],
        "DataGranule": {
          "DayNightFlag": "Both",
          "ProductionDateTime": "2019-09-12T00:00:00.000Z",
          "ArchiveAndDistributionInformation": [
            {
              "Name": "Not provided",
              "Size": 37.852784,
              "SizeUnit": "NA"
            }
          ]
        },
        "Platforms": [
          {
            "ShortName": "Environmental Modeling",
            "Instruments": [
              {
                "ShortName": "Computer"
              }
            ]
          }
        ]
      }
    },
    {
      "meta": {
        "concept-type": "granule",
        "concept-id": "G1633357987-ORNL_DAAC",
        "revision-id": 1,
        "native-id": "CMS_Forest_Carbon_Stocks.forest_productivity_NAFD.tif",
        "provider-id": "ORNL_DAAC",
        "format": "application/echo10+xml",
        "revision-date": "2019-09-13T13:33:26Z"
      },
      "umm": {
        "TemporalExtent": {
          "RangeDateTime": {
            "BeginningDateTime": "1986-01-01T00:00:00.000Z",
            "EndingDateTime": "2010-12-31T00:00:00.000Z"
          }
        },
        "GranuleUR": "CMS_Forest_Carbon_Stocks.forest_productivity_NAFD.tif",
        "MeasuredParameters": [
          {
            "ParameterName": "FORESTS"
          },
          {
            "ParameterName": "CARBON"
          },
          {
            "ParameterName": "LAND USE CLASSES"
          },
          {
            "ParameterName": "BIOMASS"
          }
        ],
        "SpatialExtent": {
          "HorizontalSpatialDomain": {
            "Geometry": {
              "BoundingRectangles": [
                {
                  "WestBoundingCoordinate": -89.0103,
                  "EastBoundingCoordinate": -71.2798,
                  "NorthBoundingCoordinate": 40.8894,
                  "SouthBoundingCoordinate": 23.2283
                }
              ]
            }
          }
        },
        "ProviderDates": [
          {
            "Date": "2019-09-12T00:00:00.000Z",
            "Type": "Insert"
          },
          {
            "Date": "2019-09-13T13:33:23.000Z",
            "Type": "Update"
          }
        ],
        "CollectionReference": {
          "ShortName": "CMS_Forest_Carbon_Stocks_1728",
          "Version": "1"
        },
        "RelatedUrls": [
          {
            "URL": "https://daac.ornl.gov/daacdata/cms/CMS_Forest_Carbon_Stocks/data/forest_productivity_NAFD.tif",
            "Type": "GET DATA",
            "Description": "This link provides direct download access to the granule."
          },
          {
            "URL": "https://daac.ornl.gov/CMS/guides/CMS_Forest_Carbon_Stocks.html",
            "Type": "VIEW RELATED INFORMATION",
            "Description": "ORNL DAAC Data Set Documentation"
          },
          {
            "URL": "https://dx.doi.org/10.3334/ORNLDAAC/1728",
            "Type": "VIEW RELATED INFORMATION",
            "Description": "Data set Landing Page DOI URL"
          },
          {
            "URL": "https:/daac.ornl.gov/daacdata/cms/CMS_Forest_Carbon_Stocks/comp/CMS_Forest_Carbon_Stocks.pdf",
            "Type": "VIEW RELATED INFORMATION",
            "Description": "Data Set Documentation"
          }
        ],
        "Projects": [
          {
            "ShortName": "Not provided",
            "Campaigns": [
              "CMS"
            ]
          }
        ],
        "DataGranule": {
          "DayNightFlag": "Both",
          "ProductionDateTime": "2019-09-12T00:00:00.000Z",
          "ArchiveAndDistributionInformation": [
            {
              "Name": "Not provided",
              "Size": 433.84748,
              "SizeUnit": "NA"
            }
          ]
        },
        "Platforms": [
          {
            "ShortName": "Environmental Modeling",
            "Instruments": [
              {
                "ShortName": "Computer"
              }
            ]
          }
        ]
      }
    },
    {
      "meta": {
        "concept-type": "granule",
        "concept-id": "G1633357988-ORNL_DAAC",
        "revision-id": 1,
        "native-id": "CMS_Forest_Carbon_Stocks.years_disturb_composite.tif",
        "provider-id": "ORNL_DAAC",
        "format": "application/echo10+xml",
        "revision-date": "2019-09-13T13:33:26Z"
      },
      "umm": {
        "TemporalExtent": {
          "RangeDateTime": {
            "BeginningDateTime": "1986-01-01T00:00:00.000Z",
            "EndingDateTime": "2010-12-31T00:00:00.000Z"
          }
        },
        "GranuleUR": "CMS_Forest_Carbon_Stocks.years_disturb_composite.tif",
        "MeasuredParameters": [
          {
            "ParameterName": "FORESTS"
          },
          {
            "ParameterName": "CARBON"
          },
          {
            "ParameterName": "LAND USE CLASSES"
          },
          {
            "ParameterName": "BIOMASS"
          }
        ],
        "SpatialExtent": {
          "HorizontalSpatialDomain": {
            "Geometry": {
              "BoundingRectangles": [
                {
                  "WestBoundingCoordinate": -89.0103,
                  "EastBoundingCoordinate": -71.2798,
                  "NorthBoundingCoordinate": 40.8894,
                  "SouthBoundingCoordinate": 23.2283
                }
              ]
            }
          }
        },
        "ProviderDates": [
          {
            "Date": "2019-09-12T00:00:00.000Z",
            "Type": "Insert"
          },
          {
            "Date": "2019-09-13T13:33:23.000Z",
            "Type": "Update"
          }
        ],
        "CollectionReference": {
          "ShortName": "CMS_Forest_Carbon_Stocks_1728",
          "Version": "1"
        },
        "RelatedUrls": [
          {
            "URL": "https://daac.ornl.gov/daacdata/cms/CMS_Forest_Carbon_Stocks/data/years_disturb_composite.tif",
            "Type": "GET DATA",
            "Description": "This link provides direct download access to the granule."
          },
          {
            "URL": "https://daac.ornl.gov/CMS/guides/CMS_Forest_Carbon_Stocks.html",
            "Type": "VIEW RELATED INFORMATION",
            "Description": "ORNL DAAC Data Set Documentation"
          },
          {
            "URL": "https://dx.doi.org/10.3334/ORNLDAAC/1728",
            "Type": "VIEW RELATED INFORMATION",
            "Description": "Data set Landing Page DOI URL"
          },
          {
            "URL": "https:/daac.ornl.gov/daacdata/cms/CMS_Forest_Carbon_Stocks/comp/CMS_Forest_Carbon_Stocks.pdf",
            "Type": "VIEW RELATED INFORMATION",
            "Description": "Data Set Documentation"
          }
        ],
        "Projects": [
          {
            "ShortName": "Not provided",
            "Campaigns": [
              "CMS"
            ]
          }
        ],
        "DataGranule": {
          "DayNightFlag": "Both",
          "ProductionDateTime": "2019-09-12T00:00:00.000Z",
          "ArchiveAndDistributionInformation": [
            {
              "Name": "Not provided",
              "Size": 215.286065,
              "SizeUnit": "NA"
            }
          ]
        },
        "Platforms": [
          {
            "ShortName": "Environmental Modeling",
            "Instruments": [
              {
                "ShortName": "Computer"
              }
            ]
          }
        ]
      }
    },
    {
      "meta": {
        "concept-type": "granule",
        "concept-id": "G1633357986-ORNL_DAAC",
        "revision-id": 1,
        "native-id": "CMS_Forest_Carbon_Stocks.age_1990.tif",
        "provider-id": "ORNL_DAAC",
        "format": "application/echo10+xml",
        "revision-date": "2019-09-13T13:33:26Z"
      },
      "umm": {
        "TemporalExtent": {
          "RangeDateTime": {
            "BeginningDateTime": "1990-01-01T00:00:00.000Z",
            "EndingDateTime": "1990-12-31T00:00:00.000Z"
          }
        },
        "GranuleUR": "CMS_Forest_Carbon_Stocks.age_1990.tif",
        "MeasuredParameters": [
          {
            "ParameterName": "FORESTS"
          },
          {
            "ParameterName": "CARBON"
          },
          {
            "ParameterName": "LAND USE CLASSES"
          },
          {
            "ParameterName": "BIOMASS"
          }
        ],
        "SpatialExtent": {
          "HorizontalSpatialDomain": {
            "Geometry": {
              "BoundingRectangles": [
                {
                  "WestBoundingCoordinate": -88.1128,
                  "EastBoundingCoordinate": -74.4978,
                  "NorthBoundingCoordinate": 40.3452,
                  "SouthBoundingCoordinate": 24.5397
                }
              ]
            }
          }
        },
        "ProviderDates": [
          {
            "Date": "2019-09-12T00:00:00.000Z",
            "Type": "Insert"
          },
          {
            "Date": "2019-09-13T13:33:23.000Z",
            "Type": "Update"
          }
        ],
        "CollectionReference": {
          "ShortName": "CMS_Forest_Carbon_Stocks_1728",
          "Version": "1"
        },
        "RelatedUrls": [
          {
            "URL": "https://daac.ornl.gov/daacdata/cms/CMS_Forest_Carbon_Stocks/data/age_1990.tif",
            "Type": "GET DATA",
            "Description": "This link provides direct download access to the granule."
          },
          {
            "URL": "https://daac.ornl.gov/CMS/guides/CMS_Forest_Carbon_Stocks.html",
            "Type": "VIEW RELATED INFORMATION",
            "Description": "ORNL DAAC Data Set Documentation"
          },
          {
            "URL": "https://dx.doi.org/10.3334/ORNLDAAC/1728",
            "Type": "VIEW RELATED INFORMATION",
            "Description": "Data set Landing Page DOI URL"
          },
          {
            "URL": "https:/daac.ornl.gov/daacdata/cms/CMS_Forest_Carbon_Stocks/comp/CMS_Forest_Carbon_Stocks.pdf",
            "Type": "VIEW RELATED INFORMATION",
            "Description": "Data Set Documentation"
          }
        ],
        "Projects": [
          {
            "ShortName": "Not provided",
            "Campaigns": [
              "CMS"
            ]
          }
        ],
        "DataGranule": {
          "DayNightFlag": "Both",
          "ProductionDateTime": "2019-09-12T00:00:00.000Z",
          "ArchiveAndDistributionInformation": [
            {
              "Name": "Not provided",
              "Size": 547.146197,
              "SizeUnit": "NA"
            }
          ]
        },
        "Platforms": [
          {
            "ShortName": "Environmental Modeling",
            "Instruments": [
              {
                "ShortName": "Computer"
              }
            ]
          }
        ]
      }
    },
    {
      "meta": {
        "concept-type": "granule",
        "concept-id": "G1633357990-ORNL_DAAC",
        "revision-id": 1,
        "native-id": "CMS_Forest_Carbon_Stocks.nep_1990.tif",
        "provider-id": "ORNL_DAAC",
        "format": "application/echo10+xml",
        "revision-date": "2019-09-13T13:33:26Z"
      },
      "umm": {
        "TemporalExtent": {
          "RangeDateTime": {
            "BeginningDateTime": "1990-01-01T00:00:00.000Z",
            "EndingDateTime": "1990-12-31T00:00:00.000Z"
          }
        },
        "GranuleUR": "CMS_Forest_Carbon_Stocks.nep_1990.tif",
        "MeasuredParameters": [
          {
            "ParameterName": "FORESTS"
          },
          {
            "ParameterName": "CARBON"
          },
          {
            "ParameterName": "LAND USE CLASSES"
          },
          {
            "ParameterName": "BIOMASS"
          }
        ],
        "SpatialExtent": {
          "HorizontalSpatialDomain": {
            "Geometry": {
              "BoundingRectangles": [
                {
                  "WestBoundingCoordinate": -88.1128,
                  "EastBoundingCoordinate": -74.4978,
                  "NorthBoundingCoordinate": 40.3452,
                  "SouthBoundingCoordinate": 24.5397
                }
              ]
            }
          }
        },
        "ProviderDates": [
          {
            "Date": "2019-09-12T00:00:00.000Z",
            "Type": "Insert"
          },
          {
            "Date": "2019-09-13T13:33:23.000Z",
            "Type": "Update"
          }
        ],
        "CollectionReference": {
          "ShortName": "CMS_Forest_Carbon_Stocks_1728",
          "Version": "1"
        },
        "RelatedUrls": [
          {
            "URL": "https://daac.ornl.gov/daacdata/cms/CMS_Forest_Carbon_Stocks/data/nep_1990.tif",
            "Type": "GET DATA",
            "Description": "This link provides direct download access to the granule."
          },
          {
            "URL": "https://daac.ornl.gov/CMS/guides/CMS_Forest_Carbon_Stocks.html",
            "Type": "VIEW RELATED INFORMATION",
            "Description": "ORNL DAAC Data Set Documentation"
          },
          {
            "URL": "https://dx.doi.org/10.3334/ORNLDAAC/1728",
            "Type": "VIEW RELATED INFORMATION",
            "Description": "Data set Landing Page DOI URL"
          },
          {
            "URL": "https:/daac.ornl.gov/daacdata/cms/CMS_Forest_Carbon_Stocks/comp/CMS_Forest_Carbon_Stocks.pdf",
            "Type": "VIEW RELATED INFORMATION",
            "Description": "Data Set Documentation"
          }
        ],
        "Projects": [
          {
            "ShortName": "Not provided",
            "Campaigns": [
              "CMS"
            ]
          }
        ],
        "DataGranule": {
          "DayNightFlag": "Both",
          "ProductionDateTime": "2019-09-12T00:00:00.000Z",
          "ArchiveAndDistributionInformation": [
            {
              "Name": "Not provided",
              "Size": 729.448225,
              "SizeUnit": "NA"
            }
          ]
        },
        "Platforms": [
          {
            "ShortName": "Environmental Modeling",
            "Instruments": [
              {
                "ShortName": "Computer"
              }
            ]
          }
        ]
      }
    },
    {
      "meta": {
        "concept-type": "granule",
        "concept-id": "G1633357991-ORNL_DAAC",
        "revision-id": 1,
        "native-id": "CMS_Forest_Carbon_Stocks.agb_1990.tif",
        "provider-id": "ORNL_DAAC",
        "format": "application/echo10+xml",
        "revision-date": "2019-09-13T13:33:26Z"
      },
      "umm": {
        "TemporalExtent": {
          "RangeDateTime": {
            "BeginningDateTime": "1990-01-01T00:00:00.000Z",
            "EndingDateTime": "1990-12-31T00:00:00.000Z"
          }
        },
        "GranuleUR": "CMS_Forest_Carbon_Stocks.agb_1990.tif",
        "MeasuredParameters": [
          {
            "ParameterName": "FORESTS"
          },
          {
            "ParameterName": "CARBON"
          },
          {
            "ParameterName": "LAND USE CLASSES"
          },
          {
            "ParameterName": "BIOMASS"
          }
        ],
        "SpatialExtent": {
          "HorizontalSpatialDomain": {
            "Geometry": {
              "BoundingRectangles": [
                {
                  "WestBoundingCoordinate": -88.1128,
                  "EastBoundingCoordinate": -74.4978,
                  "NorthBoundingCoordinate": 40.3452,
                  "SouthBoundingCoordinate": 24.5397
                }
              ]
            }
          }
        },
        "ProviderDates": [
          {
            "Date": "2019-09-12T00:00:00.000Z",
            "Type": "Insert"
          },
          {
            "Date": "2019-09-13T13:33:23.000Z",
            "Type": "Update"
          }
        ],
        "CollectionReference": {
          "ShortName": "CMS_Forest_Carbon_Stocks_1728",
          "Version": "1"
        },
        "RelatedUrls": [
          {
            "URL": "https://daac.ornl.gov/daacdata/cms/CMS_Forest_Carbon_Stocks/data/agb_1990.tif",
            "Type": "GET DATA",
            "Description": "This link provides direct download access to the granule."
          },
          {
            "URL": "https://daac.ornl.gov/CMS/guides/CMS_Forest_Carbon_Stocks.html",
            "Type": "VIEW RELATED INFORMATION",
            "Description": "ORNL DAAC Data Set Documentation"
          },
          {
            "URL": "https://dx.doi.org/10.3334/ORNLDAAC/1728",
            "Type": "VIEW RELATED INFORMATION",
            "Description": "Data set Landing Page DOI URL"
          },
          {
            "URL": "https:/daac.ornl.gov/daacdata/cms/CMS_Forest_Carbon_Stocks/comp/CMS_Forest_Carbon_Stocks.pdf",
            "Type": "VIEW RELATED INFORMATION",
            "Description": "Data Set Documentation"
          }
        ],
        "Projects": [
          {
            "ShortName": "Not provided",
            "Campaigns": [
              "CMS"
            ]
          }
        ],
        "DataGranule": {
          "DayNightFlag": "Both",
          "ProductionDateTime": "2019-09-12T00:00:00.000Z",
          "ArchiveAndDistributionInformation": [
            {
              "Name": "Not provided",
              "Size": 1104.325951,
              "SizeUnit": "NA"
            }
          ]
        },
        "Platforms": [
          {
            "ShortName": "Environmental Modeling",
            "Instruments": [
              {
                "ShortName": "Computer"
              }
            ]
          }
        ]
      }
    },
    {
      "meta": {
        "concept-type": "granule",
        "concept-id": "G1633357977-ORNL_DAAC",
        "revision-id": 1,
        "native-id": "CMS_Forest_Carbon_Stocks.agb_2000.tif",
        "provider-id": "ORNL_DAAC",
        "format": "application/echo10+xml",
        "revision-date": "2019-09-13T13:33:26Z"
      },
      "umm": {
        "TemporalExtent": {
          "RangeDateTime": {
            "BeginningDateTime": "2000-01-01T00:00:00.000Z",
            "EndingDateTime": "2000-12-31T00:00:00.000Z"
          }
        },
        "GranuleUR": "CMS_Forest_Carbon_Stocks.agb_2000.tif",
        "MeasuredParameters": [
          {
            "ParameterName": "FORESTS"
          },
          {
            "ParameterName": "CARBON"
          },
          {
            "ParameterName": "LAND USE CLASSES"
          },
          {
            "ParameterName": "BIOMASS"
          }
        ],
        "SpatialExtent": {
          "HorizontalSpatialDomain": {
            "Geometry": {
              "BoundingRectangles": [
                {
                  "WestBoundingCoordinate": -88.1128,
                  "EastBoundingCoordinate": -74.4978,
                  "NorthBoundingCoordinate": 40.3452,
                  "SouthBoundingCoordinate": 24.5397
                }
              ]
            }
          }
        },
        "ProviderDates": [
          {
            "Date": "2019-09-12T00:00:00.000Z",
            "Type": "Insert"
          },
          {
            "Date": "2019-09-13T13:33:23.000Z",
            "Type": "Update"
          }
        ],
        "CollectionReference": {
          "ShortName": "CMS_Forest_Carbon_Stocks_1728",
          "Version": "1"
        },
        "RelatedUrls": [
          {
            "URL": "https://daac.ornl.gov/daacdata/cms/CMS_Forest_Carbon_Stocks/data/agb_2000.tif",
            "Type": "GET DATA",
            "Description": "This link provides direct download access to the granule."
          },
          {
            "URL": "https://daac.ornl.gov/CMS/guides/CMS_Forest_Carbon_Stocks.html",
            "Type": "VIEW RELATED INFORMATION",
            "Description": "ORNL DAAC Data Set Documentation"
          },
          {
            "URL": "https://dx.doi.org/10.3334/ORNLDAAC/1728",
            "Type": "VIEW RELATED INFORMATION",
            "Description": "Data set Landing Page DOI URL"
          },
          {
            "URL": "https:/daac.ornl.gov/daacdata/cms/CMS_Forest_Carbon_Stocks/comp/CMS_Forest_Carbon_Stocks.pdf",
            "Type": "VIEW RELATED INFORMATION",
            "Description": "Data Set Documentation"
          }
        ],
        "Projects": [
          {
            "ShortName": "Not provided",
            "Campaigns": [
              "CMS"
            ]
          }
        ],
        "DataGranule": {
          "DayNightFlag": "Both",
          "ProductionDateTime": "2019-09-12T00:00:00.000Z",
          "ArchiveAndDistributionInformation": [
            {
              "Name": "Not provided",
              "Size": 1100.850381,
              "SizeUnit": "NA"
            }
          ]
        },
        "Platforms": [
          {
            "ShortName": "Environmental Modeling",
            "Instruments": [
              {
                "ShortName": "Computer"
              }
            ]
          }
        ]
      }
    },
    {
      "meta": {
        "concept-type": "granule",
        "concept-id": "G1633357978-ORNL_DAAC",
        "revision-id": 1,
        "native-id": "CMS_Forest_Carbon_Stocks.biomass_NBCD.tif",
        "provider-id": "ORNL_DAAC",
        "format": "application/echo10+xml",
        "revision-date": "2019-09-13T13:33:26Z"
      },
      "umm": {
        "TemporalExtent": {
          "RangeDateTime": {
            "BeginningDateTime": "2000-01-01T00:00:00.000Z",
            "EndingDateTime": "2000-12-31T00:00:00.000Z"
          }
        },
        "GranuleUR": "CMS_Forest_Carbon_Stocks.biomass_NBCD.tif",
        "MeasuredParameters": [
          {
            "ParameterName": "FORESTS"
          },
          {
            "ParameterName": "CARBON"
          },
          {
            "ParameterName": "LAND USE CLASSES"
          },
          {
            "ParameterName": "BIOMASS"
          }
        ],
        "SpatialExtent": {
          "HorizontalSpatialDomain": {
            "Geometry": {
              "BoundingRectangles": [
                {
                  "WestBoundingCoordinate": -89.0103,
                  "EastBoundingCoordinate": -74.1394,
                  "NorthBoundingCoordinate": 40.8894,
                  "SouthBoundingCoordinate": 23.6938
                }
              ]
            }
          }
        },
        "ProviderDates": [
          {
            "Date": "2019-09-12T00:00:00.000Z",
            "Type": "Insert"
          },
          {
            "Date": "2019-09-13T13:33:23.000Z",
            "Type": "Update"
          }
        ],
        "CollectionReference": {
          "ShortName": "CMS_Forest_Carbon_Stocks_1728",
          "Version": "1"
        },
        "RelatedUrls": [
          {
            "URL": "https://daac.ornl.gov/daacdata/cms/CMS_Forest_Carbon_Stocks/data/biomass_NBCD.tif",
            "Type": "GET DATA",
            "Description": "This link provides direct download access to the granule."
          },
          {
            "URL": "https://daac.ornl.gov/CMS/guides/CMS_Forest_Carbon_Stocks.html",
            "Type": "VIEW RELATED INFORMATION",
            "Description": "ORNL DAAC Data Set Documentation"
          },
          {
            "URL": "https://dx.doi.org/10.3334/ORNLDAAC/1728",
            "Type": "VIEW RELATED INFORMATION",
            "Description": "Data set Landing Page DOI URL"
          },
          {
            "URL": "https:/daac.ornl.gov/daacdata/cms/CMS_Forest_Carbon_Stocks/comp/CMS_Forest_Carbon_Stocks.pdf",
            "Type": "VIEW RELATED INFORMATION",
            "Description": "Data Set Documentation"
          }
        ],
        "Projects": [
          {
            "ShortName": "Not provided",
            "Campaigns": [
              "CMS"
            ]
          }
        ],
        "DataGranule": {
          "DayNightFlag": "Both",
          "ProductionDateTime": "2019-09-12T00:00:00.000Z",
          "ArchiveAndDistributionInformation": [
            {
              "Name": "Not provided",
              "Size": 780.756166,
              "SizeUnit": "NA"
            }
          ]
        },
        "Platforms": [
          {
            "ShortName": "Environmental Modeling",
            "Instruments": [
              {
                "ShortName": "Computer"
              }
            ]
          }
        ]
      }
    },
    {
      "meta": {
        "concept-type": "granule",
        "concept-id": "G1633357983-ORNL_DAAC",
        "revision-id": 1,
        "native-id": "CMS_Forest_Carbon_Stocks.age_2000.tif",
        "provider-id": "ORNL_DAAC",
        "format": "application/echo10+xml",
        "revision-date": "2019-09-13T13:33:26Z"
      },
      "umm": {
        "TemporalExtent": {
          "RangeDateTime": {
            "BeginningDateTime": "2000-01-01T00:00:00.000Z",
            "EndingDateTime": "2000-12-31T00:00:00.000Z"
          }
        },
        "GranuleUR": "CMS_Forest_Carbon_Stocks.age_2000.tif",
        "MeasuredParameters": [
          {
            "ParameterName": "FORESTS"
          },
          {
            "ParameterName": "CARBON"
          },
          {
            "ParameterName": "LAND USE CLASSES"
          },
          {
            "ParameterName": "BIOMASS"
          }
        ],
        "SpatialExtent": {
          "HorizontalSpatialDomain": {
            "Geometry": {
              "BoundingRectangles": [
                {
                  "WestBoundingCoordinate": -88.1128,
                  "EastBoundingCoordinate": -74.4978,
                  "NorthBoundingCoordinate": 40.3452,
                  "SouthBoundingCoordinate": 24.5397
                }
              ]
            }
          }
        },
        "ProviderDates": [
          {
            "Date": "2019-09-12T00:00:00.000Z",
            "Type": "Insert"
          },
          {
            "Date": "2019-09-13T13:33:23.000Z",
            "Type": "Update"
          }
        ],
        "CollectionReference": {
          "ShortName": "CMS_Forest_Carbon_Stocks_1728",
          "Version": "1"
        },
        "RelatedUrls": [
          {
            "URL": "https://daac.ornl.gov/daacdata/cms/CMS_Forest_Carbon_Stocks/data/age_2000.tif",
            "Type": "GET DATA",
            "Description": "This link provides direct download access to the granule."
          },
          {
            "URL": "https://daac.ornl.gov/CMS/guides/CMS_Forest_Carbon_Stocks.html",
            "Type": "VIEW RELATED INFORMATION",
            "Description": "ORNL DAAC Data Set Documentation"
          },
          {
            "URL": "https://dx.doi.org/10.3334/ORNLDAAC/1728",
            "Type": "VIEW RELATED INFORMATION",
            "Description": "Data set Landing Page DOI URL"
          },
          {
            "URL": "https:/daac.ornl.gov/daacdata/cms/CMS_Forest_Carbon_Stocks/comp/CMS_Forest_Carbon_Stocks.pdf",
            "Type": "VIEW RELATED INFORMATION",
            "Description": "Data Set Documentation"
          }
        ],
        "Projects": [
          {
            "ShortName": "Not provided",
            "Campaigns": [
              "CMS"
            ]
          }
        ],
        "DataGranule": {
          "DayNightFlag": "Both",
          "ProductionDateTime": "2019-09-12T00:00:00.000Z",
          "ArchiveAndDistributionInformation": [
            {
              "Name": "Not provided",
              "Size": 550.250656,
              "SizeUnit": "NA"
            }
          ]
        },
        "Platforms": [
          {
            "ShortName": "Environmental Modeling",
            "Instruments": [
              {
                "ShortName": "Computer"
              }
            ]
          }
        ]
      }
    },
    {
      "meta": {
        "concept-type": "granule",
        "concept-id": "G1633357992-ORNL_DAAC",
        "revision-id": 1,
        "native-id": "CMS_Forest_Carbon_Stocks.nep_2000.tif",
        "provider-id": "ORNL_DAAC",
        "format": "application/echo10+xml",
        "revision-date": "2019-09-13T13:33:26Z"
      },
      "umm": {
        "TemporalExtent": {
          "RangeDateTime": {
            "BeginningDateTime": "2000-01-01T00:00:00.000Z",
            "EndingDateTime": "2000-12-31T00:00:00.000Z"
          }
        },
        "GranuleUR": "CMS_Forest_Carbon_Stocks.nep_2000.tif",
        "MeasuredParameters": [
          {
            "ParameterName": "FORESTS"
          },
          {
            "ParameterName": "CARBON"
          },
          {
            "ParameterName": "LAND USE CLASSES"
          },
          {
            "ParameterName": "BIOMASS"
          }
        ],
        "SpatialExtent": {
          "HorizontalSpatialDomain": {
            "Geometry": {
              "BoundingRectangles": [
                {
                  "WestBoundingCoordinate": -88.1128,
                  "EastBoundingCoordinate": -74.4978,
                  "NorthBoundingCoordinate": 40.3452,
                  "SouthBoundingCoordinate": 24.5397
                }
              ]
            }
          }
        },
        "ProviderDates": [
          {
            "Date": "2019-09-12T00:00:00.000Z",
            "Type": "Insert"
          },
          {
            "Date": "2019-09-13T13:33:23.000Z",
            "Type": "Update"
          }
        ],
        "CollectionReference": {
          "ShortName": "CMS_Forest_Carbon_Stocks_1728",
          "Version": "1"
        },
        "RelatedUrls": [
          {
            "URL": "https://daac.ornl.gov/daacdata/cms/CMS_Forest_Carbon_Stocks/data/nep_2000.tif",
            "Type": "GET DATA",
            "Description": "This link provides direct download access to the granule."
          },
          {
            "URL": "https://daac.ornl.gov/CMS/guides/CMS_Forest_Carbon_Stocks.html",
            "Type": "VIEW RELATED INFORMATION",
            "Description": "ORNL DAAC Data Set Documentation"
          },
          {
            "URL": "https://dx.doi.org/10.3334/ORNLDAAC/1728",
            "Type": "VIEW RELATED INFORMATION",
            "Description": "Data set Landing Page DOI URL"
          },
          {
            "URL": "https:/daac.ornl.gov/daacdata/cms/CMS_Forest_Carbon_Stocks/comp/CMS_Forest_Carbon_Stocks.pdf",
            "Type": "VIEW RELATED INFORMATION",
            "Description": "Data Set Documentation"
          }
        ],
        "Projects": [
          {
            "ShortName": "Not provided",
            "Campaigns": [
              "CMS"
            ]
          }
        ],
        "DataGranule": {
          "DayNightFlag": "Both",
          "ProductionDateTime": "2019-09-12T00:00:00.000Z",
          "ArchiveAndDistributionInformation": [
            {
              "Name": "Not provided",
              "Size": 753.587169,
              "SizeUnit": "NA"
            }
          ]
        },
        "Platforms": [
          {
            "ShortName": "Environmental Modeling",
            "Instruments": [
              {
                "ShortName": "Computer"
              }
            ]
          }
        ]
      }
    },
    {
      "meta": {
        "concept-type": "granule",
        "concept-id": "G1633357981-ORNL_DAAC",
        "revision-id": 1,
        "native-id": "CMS_Forest_Carbon_Stocks.agb_2010.tif",
        "provider-id": "ORNL_DAAC",
        "format": "application/echo10+xml",
        "revision-date": "2019-09-13T13:33:26Z"
      },
      "umm": {
        "TemporalExtent": {
          "RangeDateTime": {
            "BeginningDateTime": "2010-01-01T00:00:00.000Z",
            "EndingDateTime": "2010-12-31T00:00:00.000Z"
          }
        },
        "GranuleUR": "CMS_Forest_Carbon_Stocks.agb_2010.tif",
        "MeasuredParameters": [
          {
            "ParameterName": "FORESTS"
          },
          {
            "ParameterName": "CARBON"
          },
          {
            "ParameterName": "LAND USE CLASSES"
          },
          {
            "ParameterName": "BIOMASS"
          }
        ],
        "SpatialExtent": {
          "HorizontalSpatialDomain": {
            "Geometry": {
              "BoundingRectangles": [
                {
                  "WestBoundingCoordinate": -88.1128,
                  "EastBoundingCoordinate": -74.4978,
                  "NorthBoundingCoordinate": 40.3452,
                  "SouthBoundingCoordinate": 24.5397
                }
              ]
            }
          }
        },
        "ProviderDates": [
          {
            "Date": "2019-09-12T00:00:00.000Z",
            "Type": "Insert"
          },
          {
            "Date": "2019-09-13T13:33:23.000Z",
            "Type": "Update"
          }
        ],
        "CollectionReference": {
          "ShortName": "CMS_Forest_Carbon_Stocks_1728",
          "Version": "1"
        },
        "RelatedUrls": [
          {
            "URL": "https://daac.ornl.gov/daacdata/cms/CMS_Forest_Carbon_Stocks/data/agb_2010.tif",
            "Type": "GET DATA",
            "Description": "This link provides direct download access to the granule."
          },
          {
            "URL": "https://daac.ornl.gov/CMS/guides/CMS_Forest_Carbon_Stocks.html",
            "Type": "VIEW RELATED INFORMATION",
            "Description": "ORNL DAAC Data Set Documentation"
          },
          {
            "URL": "https://dx.doi.org/10.3334/ORNLDAAC/1728",
            "Type": "VIEW RELATED INFORMATION",
            "Description": "Data set Landing Page DOI URL"
          },
          {
            "URL": "https:/daac.ornl.gov/daacdata/cms/CMS_Forest_Carbon_Stocks/comp/CMS_Forest_Carbon_Stocks.pdf",
            "Type": "VIEW RELATED INFORMATION",
            "Description": "Data Set Documentation"
          }
        ],
        "Projects": [
          {
            "ShortName": "Not provided",
            "Campaigns": [
              "CMS"
            ]
          }
        ],
        "DataGranule": {
          "DayNightFlag": "Both",
          "ProductionDateTime": "2019-09-12T00:00:00.000Z",
          "ArchiveAndDistributionInformation": [
            {
              "Name": "Not provided",
              "Size": 1035.610396,
              "SizeUnit": "NA"
            }
          ]
        },
        "Platforms": [
          {
            "ShortName": "Environmental Modeling",
            "Instruments": [
              {
                "ShortName": "Computer"
              }
            ]
          }
        ]
      }
    },
    {
      "meta": {
        "concept-type": "granule",
        "concept-id": "G1633357982-ORNL_DAAC",
        "revision-id": 1,
        "native-id": "CMS_Forest_Carbon_Stocks.nep_2010.tif",
        "provider-id": "ORNL_DAAC",
        "format": "application/echo10+xml",
        "revision-date": "2019-09-13T13:33:26Z"
      },
      "umm": {
        "TemporalExtent": {
          "RangeDateTime": {
            "BeginningDateTime": "2010-01-01T00:00:00.000Z",
            "EndingDateTime": "2010-12-31T00:00:00.000Z"
          }
        },
        "GranuleUR": "CMS_Forest_Carbon_Stocks.nep_2010.tif",
        "MeasuredParameters": [
          {
            "ParameterName": "FORESTS"
          },
          {
            "ParameterName": "CARBON"
          },
          {
            "ParameterName": "LAND USE CLASSES"
          },
          {
            "ParameterName": "BIOMASS"
          }
        ],
        "SpatialExtent": {
          "HorizontalSpatialDomain": {
            "Geometry": {
              "BoundingRectangles": [
                {
                  "WestBoundingCoordinate": -88.1128,
                  "EastBoundingCoordinate": -74.4978,
                  "NorthBoundingCoordinate": 40.3452,
                  "SouthBoundingCoordinate": 24.5397
                }
              ]
            }
          }
        },
        "ProviderDates": [
          {
            "Date": "2019-09-12T00:00:00.000Z",
            "Type": "Insert"
          },
          {
            "Date": "2019-09-13T13:33:23.000Z",
            "Type": "Update"
          }
        ],
        "CollectionReference": {
          "ShortName": "CMS_Forest_Carbon_Stocks_1728",
          "Version": "1"
        },
        "RelatedUrls": [
          {
            "URL": "https://daac.ornl.gov/daacdata/cms/CMS_Forest_Carbon_Stocks/data/nep_2010.tif",
            "Type": "GET DATA",
            "Description": "This link provides direct download access to the granule."
          },
          {
            "URL": "https://daac.ornl.gov/CMS/guides/CMS_Forest_Carbon_Stocks.html",
            "Type": "VIEW RELATED INFORMATION",
            "Description": "ORNL DAAC Data Set Documentation"
          },
          {
            "URL": "https://dx.doi.org/10.3334/ORNLDAAC/1728",
            "Type": "VIEW RELATED INFORMATION",
            "Description": "Data set Landing Page DOI URL"
          },
          {
            "URL": "https:/daac.ornl.gov/daacdata/cms/CMS_Forest_Carbon_Stocks/comp/CMS_Forest_Carbon_Stocks.pdf",
            "Type": "VIEW RELATED INFORMATION",
            "Description": "Data Set Documentation"
          }
        ],
        "Projects": [
          {
            "ShortName": "Not provided",
            "Campaigns": [
              "CMS"
            ]
          }
        ],
        "DataGranule": {
          "DayNightFlag": "Both",
          "ProductionDateTime": "2019-09-12T00:00:00.000Z",
          "ArchiveAndDistributionInformation": [
            {
              "Name": "Not provided",
              "Size": 763.166702,
              "SizeUnit": "NA"
            }
          ]
        },
        "Platforms": [
          {
            "ShortName": "Environmental Modeling",
            "Instruments": [
              {
                "ShortName": "Computer"
              }
            ]
          }
        ]
      }
    },
    {
      "meta": {
        "concept-type": "granule",
        "concept-id": "G1633357989-ORNL_DAAC",
        "revision-id": 1,
        "native-id": "CMS_Forest_Carbon_Stocks.age_2010.tif",
        "provider-id": "ORNL_DAAC",
        "format": "application/echo10+xml",
        "revision-date": "2019-09-13T13:33:26Z"
      },
      "umm": {
        "TemporalExtent": {
          "RangeDateTime": {
            "BeginningDateTime": "2010-01-01T00:00:00.000Z",
            "EndingDateTime": "2010-12-31T00:00:00.000Z"
          }
        },
        "GranuleUR": "CMS_Forest_Carbon_Stocks.age_2010.tif",
        "MeasuredParameters": [
          {
            "ParameterName": "FORESTS"
          },
          {
            "ParameterName": "CARBON"
          },
          {
            "ParameterName": "LAND USE CLASSES"
          },
          {
            "ParameterName": "BIOMASS"
          }
        ],
        "SpatialExtent": {
          "HorizontalSpatialDomain": {
            "Geometry": {
              "BoundingRectangles": [
                {
                  "WestBoundingCoordinate": -88.1128,
                  "EastBoundingCoordinate": -74.4978,
                  "NorthBoundingCoordinate": 40.3452,
                  "SouthBoundingCoordinate": 24.5397
                }
              ]
            }
          }
        },
        "ProviderDates": [
          {
            "Date": "2019-09-12T00:00:00.000Z",
            "Type": "Insert"
          },
          {
            "Date": "2019-09-13T13:33:23.000Z",
            "Type": "Update"
          }
        ],
        "CollectionReference": {
          "ShortName": "CMS_Forest_Carbon_Stocks_1728",
          "Version": "1"
        },
        "RelatedUrls": [
          {
            "URL": "https://daac.ornl.gov/daacdata/cms/CMS_Forest_Carbon_Stocks/data/age_2010.tif",
            "Type": "GET DATA",
            "Description": "This link provides direct download access to the granule."
          },
          {
            "URL": "https://daac.ornl.gov/CMS/guides/CMS_Forest_Carbon_Stocks.html",
            "Type": "VIEW RELATED INFORMATION",
            "Description": "ORNL DAAC Data Set Documentation"
          },
          {
            "URL": "https://dx.doi.org/10.3334/ORNLDAAC/1728",
            "Type": "VIEW RELATED INFORMATION",
            "Description": "Data set Landing Page DOI URL"
          },
          {
            "URL": "https:/daac.ornl.gov/daacdata/cms/CMS_Forest_Carbon_Stocks/comp/CMS_Forest_Carbon_Stocks.pdf",
            "Type": "VIEW RELATED INFORMATION",
            "Description": "Data Set Documentation"
          }
        ],
        "Projects": [
          {
            "ShortName": "Not provided",
            "Campaigns": [
              "CMS"
            ]
          }
        ],
        "DataGranule": {
          "DayNightFlag": "Both",
          "ProductionDateTime": "2019-09-12T00:00:00.000Z",
          "ArchiveAndDistributionInformation": [
            {
              "Name": "Not provided",
              "Size": 506.811354,
              "SizeUnit": "NA"
            }
          ]
        },
        "Platforms": [
          {
            "ShortName": "Environmental Modeling",
            "Instruments": [
              {
                "ShortName": "Computer"
              }
            ]
          }
        ]
      }
    }
  ]
}