{
  "hits": 3,
  "took": 66,
  "items": [
    {
      "meta": {
        "concept-type": "granule",
        "concept-id": "G1461050093-ORNL_DAAC",
        "revision-id": 1,
        "native-id": "CMS_Mangrove_Canopy_Ht_Zambezi.Zambezi_TDX_CHM.tif",
        "provider-id": "ORNL_DAAC",
        "format": "application/echo10+xml",
        "revision-date": "2018-03-26T15:56:33Z"
      },
      "umm": {
        "TemporalExtent": {
          "RangeDateTime": {
            "BeginningDateTime": "2011-10-14T00:00:00.000Z",
            "EndingDateTime": "2014-05-06T00:00:00.000Z"
          }
        },
        "GranuleUR": "CMS_Mangrove_Canopy_Ht_Zambezi.Zambezi_TDX_CHM.tif",
        "MeasuredParameters": [
          {
            "ParameterName": "DIGITAL ELEVATION/TERRAIN MODEL (DEM)"
          },
          {
            "ParameterName": "CANOPY CHARACTERISTICS"
          }
        ],
        "SpatialExtent": {
          "HorizontalSpatialDomain": {
            "Geometry": {
              "BoundingRectangles": [
                {
                  "WestBoundingCoordinate": 36.1186,
                  "EastBoundingCoordinate": 36.3389,
                  "NorthBoundingCoordinate": -18.6269,
                  "SouthBoundingCoordinate": -18.915
                }
              ]
            }
          }
        },
        "ProviderDates": [
          {
            "Date": "2017-02-28T00:00:00.000Z",
            "Type": "Insert"
          },
          {
            "Date": "2017-02-28T00:00:00.000Z",
            "Type": "Update"
          }
        ],
        "CollectionReference": {
          "ShortName": "CMS_Mangrove_Canopy_Ht_Zambezi_1357",
          "Version": "1"
        },
        "RelatedUrls": [
          {
            "URL": "https://daac.ornl.gov/daacdata/cms/CMS_Mangrove_Canopy_Ht_Zambezi/data//Zambezi_TDX_CHM.tif",
            "Type": "GET DATA",
            "Description": "This link provides direct download access to the granule."
          },
          {
            "URL": "https://daac.ornl.gov/CMS/guides/CMS_Mangrove_Canopy_Ht_Zambezi.html",
            "Type": "VIEW RELATED INFORMATION",
            "Description": "ORNL DAAC Data Set Documentation"
          },
          {
            "URL": "https://dx.doi.org/10.3334/ORNLDAAC/1357",
            "Type": "VIEW RELATED INFORMATION",
            "Description": "Data set Landing Page DOI URL"
          },
          {
            "URL": "https:/daac.ornl.gov/daacdata/cms/CMS_Mangrove_Canopy_Ht_Zambezi/comp/CMS_Mangrove_Canopy_Ht_Zambezi.pdf",
            "Type": "VIEW RELATED INFORMATION",
            "Description": "Data Set Documentation"
          },
          {
            "URL": "https://webmap.ornl.gov/sdat/pimg/1357_2.png",
            "Type": "GET RELATED VISUALIZATION",
            "Description": "Mangrove Canopy Height Estimates in Zambezi Delta, Mozambique, derived from TanDEM-X",
            "MimeType": "image/png"
          }
        ],
        "Projects": [
          {
            "ShortName": "Not provided",
            "Campaigns": [
              "CMS"
            ]
          }
        ],
        "DataGranule": {
          "DayNightFlag": "Both",
          "ProductionDateTime": "2017-02-28T00:00:00.000Z",
          "ArchiveAndDistributionInformation": [
            {
              "Name": "Not provided",
              "Size": 203.893619,
              "SizeUnit": "NA"
            }
          ]
        },
        "Platforms": [
          {
            "ShortName": "AIRCRAFT",
            "Instruments": [
              {
                "ShortName": "AIRBORNE LASER SCANNER"
              }
            ]
          },
          {
            "ShortName": "SPACE SHUTTLES",
            "Instruments": [
              {
                "ShortName": "SRTM"
              }
            ]
          },
          {
            "ShortName": "WORLDVIEW-2"
          },
          {
            "ShortName": "TSX",
            "Instruments": [
              {
                "ShortName": "SAR"
              }
            ]
          }
        ]
      }
    },
    {
      "meta": {
        "concept-type": "granule",
        "concept-id": "G1461050094-ORNL_DAAC",
        "revision-id": 1,
        "native-id": "CMS_Mangrove_Canopy_Ht_Zambezi.Zambezi_VHR_CHM.tif",
        "provider-id": "ORNL_DAAC",
        "format": "application/echo10+xml",
        "revision-date": "2018-03-26T15:56:33Z"
      },
      "umm": {
        "TemporalExtent": {
          "RangeDateTime": {
            "BeginningDateTime": "2011-10-14T00:00:00.000Z",
            "EndingDateTime": "2014-05-06T00:00:00.000Z"
          }
        },
        "GranuleUR": "CMS_Mangrove_Canopy_Ht_Zambezi.Zambezi_VHR_CHM.tif",
        "MeasuredParameters": [
          {
            "ParameterName": "DIGITAL ELEVATION/TERRAIN MODEL (DEM)"
          },
          {
            "ParameterName": "CANOPY CHARACTERISTICS"
          }
        ],
        "SpatialExtent": {
          "HorizontalSpatialDomain": {
            "Geometry": {
              "BoundingRectangles": [
                {
                  "WestBoundingCoordinate": 36.1186,
                  "EastBoundingCoordinate": 36.3389,
                  "NorthBoundingCoordinate": -18.6269,
                  "SouthBoundingCoordinate": -18.915
                }
              ]
            }
          }
        },
        "ProviderDates": [
          {
            "Date": "2017-02-28T00:00:00.000Z",
            "Type": "Insert"
          },
          {
            "Date": "2017-02-28T00:00:00.000Z",
            "Type": "Update"
          }
        ],
        "CollectionReference": {
          "ShortName": "CMS_Mangrove_Canopy_Ht_Zambezi_1357",
          "Version": "1"
        },
        "RelatedUrls": [
          {
            "URL": "https://daac.ornl.gov/daacdata/cms/CMS_Mangrove_Canopy_Ht_Zambezi/data//Zambezi_VHR_CHM.tif",
            "Type": "GET DATA",
            "Description": "This link provides direct download access to the granule."
          },
          {
            "URL": "https://daac.ornl.gov/CMS/guides/CMS_Mangrove_Canopy_Ht_Zambezi.html",
            "Type": "VIEW RELATED INFORMATION",
            "Description": "ORNL DAAC Data Set Documentation"
          },
          {
            "URL": "https://dx.doi.org/10.3334/ORNLDAAC/1357",
            "Type": "VIEW RELATED INFORMATION",
            "Description": "Data set Landing Page DOI URL"
          },
          {
            "URL": "https:/daac.ornl.gov/daacdata/cms/CMS_Mangrove_Canopy_Ht_Zambezi/comp/CMS_Mangrove_Canopy_Ht_Zambezi.pdf",
            "Type": "VIEW RELATED INFORMATION",
            "Description": "Data Set Documentation"
          },
          {
            "URL": "https://webmap.ornl.gov/sdat/pimg/1357_3.png",
            "Type": "GET RELATED VISUALIZATION",
            "Description": "Mangrove Canopy Height Estimates in Zambezi Delta, Mozambique, derived from VHR Stereo",
            "MimeType": "image/png"
          }
        ],
        "Projects": [
          {
            "ShortName": "Not provided",
            "Campaigns": [
              "CMS"
            ]
          }
        ],
        "DataGranule": {
          "DayNightFlag": "Both",
          "ProductionDateTime": "2017-02-28T00:00:00.000Z",
          "ArchiveAndDistributionInformation": [
            {
              "Name": "Not provided",
              "Size": 930.457193,
              "SizeUnit": "NA"
            }
          ]
        },
        "Platforms": [
          {
            "ShortName": "AIRCRAFT",
            "Instruments": [
              {
                "ShortName": "AIRBORNE LASER SCANNER"
              }
            ]
          },
          {
            "ShortName": "SPACE SHUTTLES",
            "Instruments": [
              {
                "ShortName": "SRTM"
              }
            ]
          },
          {
            "ShortName": "WORLDVIEW-2"
          },
          {
            "ShortName": "TSX",
            "Instruments": [
              {
                "ShortName": "SAR"
              }
            ]
          }
        ]
      }
    },
    {
      "meta": {
        "concept-type": "granule",
        "concept-id": "G1461050095-ORNL_DAAC",
        "revision-id": 1,
        "native-id": "CMS_Mangrove_Canopy_Ht_Zambezi.Zambezi_Lidar_CHM.tif",
        "provider-id": "ORNL_DAAC",
        "format": "application/echo10+xml",
        "revision-date": "2018-03-26T15:56:33Z"
      },
      "umm": {
        "TemporalExtent": {
          "RangeDateTime": {
            "BeginningDateTime": "2011-10-14T00:00:00.000Z",
            "EndingDateTime": "2014-05-06T00:00:00.000Z"
          }
        },
        "GranuleUR": "CMS_Mangrove_Canopy_Ht_Zambezi.Zambezi_Lidar_CHM.tif",
        "MeasuredParameters": [
          {
            "ParameterName": "DIGITAL ELEVATION/TERRAIN MODEL (DEM)"
          },
          {
            "ParameterName": "CANOPY CHARACTERISTICS"
          }
        ],
        "SpatialExtent": {
          "HorizontalSpatialDomain": {
            "Geometry": {
              "BoundingRectangles": [
                {
                  "WestBoundingCoordinate": 36.1186,
                  "EastBoundingCoordinate": 36.3389,
                  "NorthBoundingCoordinate": -18.6269,
                  "SouthBoundingCoordinate": -18.915
                }
              ]
            }
          }
        },
        "ProviderDates": [
          {
            "Date": "2017-02-28T00:00:00.000Z",
            "Type": "Insert"
          },
          {
            "Date": "2017-02-28T00:00:00.000Z",
            "Type": "Update"
          }
        ],
        "CollectionReference": {
          "ShortName": "CMS_Mangrove_Canopy_Ht_Zambezi_1357",
          "Version": "1"
        },
        "RelatedUrls": [
          {
            "URL": "https://daac.ornl.gov/daacdata/cms/CMS_Mangrove_Canopy_Ht_Zambezi/data//Zambezi_Lidar_CHM.tif",
            "Type": "GET DATA",
            "Description": "This link provides direct download access to the granule."
          },
          {
            "URL": "https://daac.ornl.gov/CMS/guides/CMS_Mangrove_Canopy_Ht_Zambezi.html",
            "Type": "VIEW RELATED INFORMATION",
            "Description": "ORNL DAAC Data Set Documentation"
          },
          {
            "URL": "https://dx.doi.org/10.3334/ORNLDAAC/1357",
            "Type": "VIEW RELATED INFORMATION",
            "Description": "Data set Landing Page DOI URL"
          },
          {
            "URL": "https:/daac.ornl.gov/daacdata/cms/CMS_Mangrove_Canopy_Ht_Zambezi/comp/CMS_Mangrove_Canopy_Ht_Zambezi.pdf",
            "Type": "VIEW RELATED INFORMATION",
            "Description": "Data Set Documentation"
          },
          {
            "URL": "https://webmap.ornl.gov/sdat/pimg/1357_1.png",
            "Type": "GET RELATED VISUALIZATION",
            "Description": "Mangrove Canopy Height Estimates in Zambezi Delta, Mozambique, derived from Airborne Lidar",
            "MimeType": "image/png"
          }
        ],
        "Projects": [
          {
            "ShortName": "Not provided",
            "Campaigns": [
              "CMS"
            ]
          }
        ],
        "DataGranule": {
          "DayNightFlag": "Both",
          "ProductionDateTime": "2017-02-28T00:00:00.000Z",
          "ArchiveAndDistributionInformation": [
            {
              "Name": "Not provided",
              "Size": 403.171947,
              "SizeUnit": "NA"
            }
          ]
        },
        "Platforms": [
          {
            "ShortName": "AIRCRAFT",
            "Instruments": [
              {
                "ShortName": "AIRBORNE LASER SCANNER"
              }
            ]
          },
          {
            "ShortName": "SPACE SHUTTLES",
            "Instruments": [
              {
                "ShortName": "SRTM"
              }
            ]
          },
          {
            "ShortName": "WORLDVIEW-2"
          },
          {
            "ShortName": "TSX",
            "Instruments": [
              {
                "ShortName": "SAR"
              }
            ]
          }
        ]
      }
    }
  ]
}