{
  "hits": 1,
  "took": 12,
  "items": [
    {
      "meta": {
        "concept-type": "granule",
        "concept-id": "G1422744284-ORNL_DAAC",
        "revision-id": 1,
        "native-id": "BOREAS_H03SD96D.hyd03_snow_depths_96.dat",
        "provider-id": "ORNL_DAAC",
        "format": "application/echo10+xml",
        "revision-date": "2017-09-28T16:27:54Z"
      },
      "umm": {
        "TemporalExtent": {
          "RangeDateTime": {
            "BeginningDateTime": "1996-02-29T00:00:00.000Z",
            "EndingDateTime": "1996-03-11T00:00:00.000Z"
          }
        },
        "GranuleUR": "BOREAS_H03SD96D.hyd03_snow_depths_96.dat",
        "MeasuredParameters": [
          {
            "ParameterName": "SNOW DEPTH"
          }
        ],
        "SpatialExtent": {
          "HorizontalSpatialDomain": {
            "Geometry": {
              "BoundingRectangles": [
                {
                  "WestBoundingCoordinate": -106.198,
                  "EastBoundingCoordinate": -104.692,
                  "NorthBoundingCoordinate": 53.9872,
                  "SouthBoundingCoordinate": 53.5765
                }
              ]
            }
          }
        },
        "ProviderDates": [
          {
            "Date": "1999-01-30T00:00:00.000Z",
            "Type": "Insert"
          },
          {
            "Date": "1999-01-30T00:00:00.000Z",
            "Type": "Update"
          }
        ],
        "CollectionReference": {
          "ShortName": "BOREAS_H03SD96D_259",
          "Version": "1"
        },
        "RelatedUrls": [
          {
            "URL": "https://daac.ornl.gov/daacdata/boreas/HYD/h03sd96d/data/hyd03_snow_depths_96.dat",
            "Type": "GET DATA",
            "Description": "This link provides direct download access to the granule."
          },
          {
            "URL": "https://daac.ornl.gov/BOREAS/guides/HYD03_Snow_Meas.html",
            "Type": "VIEW RELATED INFORMATION",
            "Description": "ORNL DAAC Data Set Documentation"
          },
          {
            "URL": "https://dx.doi.org/doi:10.3334/ORNLDAAC/259",
            "Type": "VIEW RELATED INFORMATION",
            "Description": "Data set Landing Page DOI URL"
          },
          {
            "URL": "https:/daac.ornl.gov/daacdata/boreas/HYD/h03sd96d/comp/h03sd96d.def",
            "Type": "VIEW RELATED INFORMATION",
            "Description": "Data Set Documentation"
          },
          {
            "URL": "https:/daac.ornl.gov/daacdata/boreas/HYD/h03sd96d/comp/HYD03_Snow_Meas.doc",
            "Type": "VIEW RELATED INFORMATION",
            "Description": "Data Set Documentation"
          },
          {
            "URL": "https:/daac.ornl.gov/daacdata/boreas/HYD/h03sd96d/comp/HYD03_Snow_Meas.pdf",
            "Type": "VIEW RELATED INFORMATION",
            "Description": "Data Set Documentation"
          },
          {
            "URL": "https:/daac.ornl.gov/daacdata/boreas/HYD/h03sd96d/comp/HYD03_Snow_Meas.txt",
            "Type": "VIEW RELATED INFORMATION",
            "Description": "Data Set Documentation"
          }
        ],
        "Projects": [
          {
            "ShortName": "Not provided",
            "Campaigns": [
              "BOREAS"
            ]
          }
        ],
        "DataGranule": {
          "DayNightFlag": "Day",
          "ProductionDateTime": "1999-01-30T00:00:00.000Z",
          "ArchiveAndDistributionInformation": [
            {
              "Name": "Not provided",
              "Size": 0.05009,
              "SizeUnit": "NA"
            }
          ]
        },
        "Platforms": [
          {
            "ShortName": "FIELD INVESTIGATION",
            "Instruments": [
              {
                "ShortName": "SNOW MEASURING ROD"
              }
            ]
          }
        ]
      }
    }
  ]
}