{
  "hits": 10,
  "took": 24,
  "items": [
    {
      "meta": {
        "concept-type": "granule",
        "concept-id": "G1633153235-ORNL_DAAC",
        "revision-id": 1,
        "native-id": "OTTER_SE590_ULTRALT.2df10830.prn",
        "provider-id": "ORNL_DAAC",
        "format": "application/echo10+xml",
        "revision-date": "2019-09-11T12:41:04Z"
      },
      "umm": {
        "TemporalExtent": {
          "RangeDateTime": {
            "BeginningDateTime": "1990-08-13T00:00:00.000Z",
            "EndingDateTime": "1990-08-13T00:00:00.000Z"
          }
        },
        "GranuleUR": "OTTER_SE590_ULTRALT.2df10830.prn",
        "MeasuredParameters": [
          {
            "ParameterName": "REFLECTANCE"
          }
        ],
        "SpatialExtent": {
          "HorizontalSpatialDomain": {
            "Geometry": {
              "Points": [
                {
                  "Longitude": -123.27,
                  "Latitude": 44.6011
                }
              ]
            }
          }
        },
        "ProviderDates": [
          {
            "Date": "1994-07-24T00:00:00.000Z",
            "Type": "Insert"
          },
          {
            "Date": "2019-09-11T12:41:02.000Z",
            "Type": "Update"
          }
        ],
        "CollectionReference": {
          "ShortName": "OTTER_SE590_ULTRALT_86",
          "Version": "1"
        },
        "RelatedUrls": [
          {
            "URL": "https://daac.ornl.gov/daacdata/otter/spectra_se590_altitude/data/2df10830.prn",
            "Type": "GET DATA",
            "Description": "This link provides direct download access to the granule."
          },
          {
            "URL": "https://daac.ornl.gov/OTTER/guides/SE590_Low_Altitude_Reflectance_Data.html",
            "Type": "VIEW RELATED INFORMATION",
            "Description": "ORNL DAAC Data Set Documentation"
          },
          {
            "URL": "https://dx.doi.org/10.3334/ORNLDAAC/86",
            "Type": "VIEW RELATED INFORMATION",
            "Description": "Data set Landing Page DOI URL"
          },
          {
            "URL": "https:/daac.ornl.gov/daacdata/otter/spectra_se590_altitude/comp/mccreigh.txt",
            "Type": "VIEW RELATED INFORMATION",
            "Description": "Data Set Documentation"
          },
          {
            "URL": "https:/daac.ornl.gov/daacdata/otter/spectra_se590_altitude/comp/se590.txt",
            "Type": "VIEW RELATED INFORMATION",
            "Description": "Data Set Documentation"
          },
          {
            "URL": "https:/daac.ornl.gov/daacdata/otter/spectra_se590_altitude/comp/SE590_Low_Altitude_Reflectance_Data.pdf",
            "Type": "VIEW RELATED INFORMATION",
            "Description": "Data Set Documentation"
          }
        ],
        "Projects": [
          {
            "ShortName": "Not provided",
            "Campaigns": [
              "OTTER"
            ]
          }
        ],
        "DataGranule": {
          "DayNightFlag": "Day",
          "ProductionDateTime": "1994-07-24T00:00:00.000Z",
          "ArchiveAndDistributionInformation": [
            {
              "Name": "Not provided",
              "Size": 0.003889,
              "SizeUnit": "NA"
            }
          ]
        },
        "Platforms": [
          {
            "ShortName": "FIELD INVESTIGATION",
            "Instruments": [
              {
                "ShortName": "SPECTRORADIOMETERS"
              }
            ]
          },
          {
            "ShortName": "AIRCRAFT",
            "Instruments": [
              {
                "ShortName": "SPECTRORADIOMETERS"
              }
            ]
          }
        ]
      }
    },
    {
      "meta": {
        "concept-type": "granule",
        "concept-id": "G1633153239-ORNL_DAAC",
        "revision-id": 1,
        "native-id": "OTTER_SE590_ULTRALT.2ow11225.prn",
        "provider-id": "ORNL_DAAC",
        "format": "application/echo10+xml",
        "revision-date": "2019-09-11T12:41:04Z"
      },
      "umm": {
        "TemporalExtent": {
          "RangeDateTime": {
            "BeginningDateTime": "1990-08-13T00:00:00.000Z",
            "EndingDateTime": "1990-08-13T00:00:00.000Z"
          }
        },
        "GranuleUR": "OTTER_SE590_ULTRALT.2ow11225.prn",
        "MeasuredParameters": [
          {
            "ParameterName": "REFLECTANCE"
          }
        ],
        "SpatialExtent": {
          "HorizontalSpatialDomain": {
            "Geometry": {
              "Points": [
                {
                  "Longitude": -123.27,
                  "Latitude": 44.6011
                }
              ]
            }
          }
        },
        "ProviderDates": [
          {
            "Date": "1994-07-24T00:00:00.000Z",
            "Type": "Insert"
          },
          {
            "Date": "2019-09-11T12:41:02.000Z",
            "Type": "Update"
          }
        ],
        "CollectionReference": {
          "ShortName": "OTTER_SE590_ULTRALT_86",
          "Version": "1"
        },
        "RelatedUrls": [
          {
            "URL": "https://daac.ornl.gov/daacdata/otter/spectra_se590_altitude/data/2ow11225.prn",
            "Type": "GET DATA",
            "Description": "This link provides direct download access to the granule."
          },
          {
            "URL": "https://daac.ornl.gov/OTTER/guides/SE590_Low_Altitude_Reflectance_Data.html",
            "Type": "VIEW RELATED INFORMATION",
            "Description": "ORNL DAAC Data Set Documentation"
          },
          {
            "URL": "https://dx.doi.org/10.3334/ORNLDAAC/86",
            "Type": "VIEW RELATED INFORMATION",
            "Description": "Data set Landing Page DOI URL"
          },
          {
            "URL": "https:/daac.ornl.gov/daacdata/otter/spectra_se590_altitude/comp/mccreigh.txt",
            "Type": "VIEW RELATED INFORMATION",
            "Description": "Data Set Documentation"
          },
          {
            "URL": "https:/daac.ornl.gov/daacdata/otter/spectra_se590_altitude/comp/se590.txt",
            "Type": "VIEW RELATED INFORMATION",
            "Description": "Data Set Documentation"
          },
          {
            "URL": "https:/daac.ornl.gov/daacdata/otter/spectra_se590_altitude/comp/SE590_Low_Altitude_Reflectance_Data.pdf",
            "Type": "VIEW RELATED INFORMATION",
            "Description": "Data Set Documentation"
          }
        ],
        "Projects": [
          {
            "ShortName": "Not provided",
            "Campaigns": [
              "OTTER"
            ]
          }
        ],
        "DataGranule": {
          "DayNightFlag": "Day",
          "ProductionDateTime": "1994-07-24T00:00:00.000Z",
          "ArchiveAndDistributionInformation": [
            {
              "Name": "Not provided",
              "Size": 0.003891,
              "SizeUnit": "NA"
            }
          ]
        },
        "Platforms": [
          {
            "ShortName": "FIELD INVESTIGATION",
            "Instruments": [
              {
                "ShortName": "SPECTRORADIOMETERS"
              }
            ]
          },
          {
            "ShortName": "AIRCRAFT",
            "Instruments": [
              {
                "ShortName": "SPECTRORADIOMETERS"
              }
            ]
          }
        ]
      }
    },
    {
      "meta": {
        "concept-type": "granule",
        "concept-id": "G1633153242-ORNL_DAAC",
        "revision-id": 1,
        "native-id": "OTTER_SE590_ULTRALT.2gf11353.prn",
        "provider-id": "ORNL_DAAC",
        "format": "application/echo10+xml",
        "revision-date": "2019-09-11T12:41:04Z"
      },
      "umm": {
        "TemporalExtent": {
          "RangeDateTime": {
            "BeginningDateTime": "1990-08-13T00:00:00.000Z",
            "EndingDateTime": "1990-08-13T00:00:00.000Z"
          }
        },
        "GranuleUR": "OTTER_SE590_ULTRALT.2gf11353.prn",
        "MeasuredParameters": [
          {
            "ParameterName": "REFLECTANCE"
          }
        ],
        "SpatialExtent": {
          "HorizontalSpatialDomain": {
            "Geometry": {
              "Points": [
                {
                  "Longitude": -123.27,
                  "Latitude": 44.6011
                }
              ]
            }
          }
        },
        "ProviderDates": [
          {
            "Date": "1994-07-24T00:00:00.000Z",
            "Type": "Insert"
          },
          {
            "Date": "2019-09-11T12:41:02.000Z",
            "Type": "Update"
          }
        ],
        "CollectionReference": {
          "ShortName": "OTTER_SE590_ULTRALT_86",
          "Version": "1"
        },
        "RelatedUrls": [
          {
            "URL": "https://daac.ornl.gov/daacdata/otter/spectra_se590_altitude/data/2gf11353.prn",
            "Type": "GET DATA",
            "Description": "This link provides direct download access to the granule."
          },
          {
            "URL": "https://daac.ornl.gov/OTTER/guides/SE590_Low_Altitude_Reflectance_Data.html",
            "Type": "VIEW RELATED INFORMATION",
            "Description": "ORNL DAAC Data Set Documentation"
          },
          {
            "URL": "https://dx.doi.org/10.3334/ORNLDAAC/86",
            "Type": "VIEW RELATED INFORMATION",
            "Description": "Data set Landing Page DOI URL"
          },
          {
            "URL": "https:/daac.ornl.gov/daacdata/otter/spectra_se590_altitude/comp/mccreigh.txt",
            "Type": "VIEW RELATED INFORMATION",
            "Description": "Data Set Documentation"
          },
          {
            "URL": "https:/daac.ornl.gov/daacdata/otter/spectra_se590_altitude/comp/se590.txt",
            "Type": "VIEW RELATED INFORMATION",
            "Description": "Data Set Documentation"
          },
          {
            "URL": "https:/daac.ornl.gov/daacdata/otter/spectra_se590_altitude/comp/SE590_Low_Altitude_Reflectance_Data.pdf",
            "Type": "VIEW RELATED INFORMATION",
            "Description": "Data Set Documentation"
          }
        ],
        "Projects": [
          {
            "ShortName": "Not provided",
            "Campaigns": [
              "OTTER"
            ]
          }
        ],
        "DataGranule": {
          "DayNightFlag": "Day",
          "ProductionDateTime": "1994-07-24T00:00:00.000Z",
          "ArchiveAndDistributionInformation": [
            {
              "Name": "Not provided",
              "Size": 0.003891,
              "SizeUnit": "NA"
            }
          ]
        },
        "Platforms": [
          {
            "ShortName": "FIELD INVESTIGATION",
            "Instruments": [
              {
                "ShortName": "SPECTRORADIOMETERS"
              }
            ]
          },
          {
            "ShortName": "AIRCRAFT",
            "Instruments": [
              {
                "ShortName": "SPECTRORADIOMETERS"
              }
            ]
          }
        ]
      }
    },
    {
      "meta": {
        "concept-type": "granule",
        "concept-id": "G1633153233-ORNL_DAAC",
        "revision-id": 1,
        "native-id": "OTTER_SE590_ULTRALT.5901007.prn",
        "provider-id": "ORNL_DAAC",
        "format": "application/echo10+xml",
        "revision-date": "2019-09-11T12:41:04Z"
      },
      "umm": {
        "TemporalExtent": {
          "RangeDateTime": {
            "BeginningDateTime": "1990-10-07T00:00:00.000Z",
            "EndingDateTime": "1990-10-07T00:00:00.000Z"
          }
        },
        "GranuleUR": "OTTER_SE590_ULTRALT.5901007.prn",
        "MeasuredParameters": [
          {
            "ParameterName": "REFLECTANCE"
          }
        ],
        "SpatialExtent": {
          "HorizontalSpatialDomain": {
            "Geometry": {
              "Points": [
                {
                  "Longitude": -121.683,
                  "Latitude": 44.3817
                }
              ]
            }
          }
        },
        "ProviderDates": [
          {
            "Date": "1994-07-24T00:00:00.000Z",
            "Type": "Insert"
          },
          {
            "Date": "2019-09-11T12:41:02.000Z",
            "Type": "Update"
          }
        ],
        "CollectionReference": {
          "ShortName": "OTTER_SE590_ULTRALT_86",
          "Version": "1"
        },
        "RelatedUrls": [
          {
            "URL": "https://daac.ornl.gov/daacdata/otter/spectra_se590_altitude/data/5901007.prn",
            "Type": "GET DATA",
            "Description": "This link provides direct download access to the granule."
          },
          {
            "URL": "https://daac.ornl.gov/OTTER/guides/SE590_Low_Altitude_Reflectance_Data.html",
            "Type": "VIEW RELATED INFORMATION",
            "Description": "ORNL DAAC Data Set Documentation"
          },
          {
            "URL": "https://dx.doi.org/10.3334/ORNLDAAC/86",
            "Type": "VIEW RELATED INFORMATION",
            "Description": "Data set Landing Page DOI URL"
          },
          {
            "URL": "https:/daac.ornl.gov/daacdata/otter/spectra_se590_altitude/comp/mccreigh.txt",
            "Type": "VIEW RELATED INFORMATION",
            "Description": "Data Set Documentation"
          },
          {
            "URL": "https:/daac.ornl.gov/daacdata/otter/spectra_se590_altitude/comp/se590.txt",
            "Type": "VIEW RELATED INFORMATION",
            "Description": "Data Set Documentation"
          },
          {
            "URL": "https:/daac.ornl.gov/daacdata/otter/spectra_se590_altitude/comp/SE590_Low_Altitude_Reflectance_Data.pdf",
            "Type": "VIEW RELATED INFORMATION",
            "Description": "Data Set Documentation"
          }
        ],
        "Projects": [
          {
            "ShortName": "Not provided",
            "Campaigns": [
              "OTTER"
            ]
          }
        ],
        "DataGranule": {
          "DayNightFlag": "Day",
          "ProductionDateTime": "1994-07-24T00:00:00.000Z",
          "ArchiveAndDistributionInformation": [
            {
              "Name": "Not provided",
              "Size": 0.005698,
              "SizeUnit": "NA"
            }
          ]
        },
        "Platforms": [
          {
            "ShortName": "FIELD INVESTIGATION",
            "Instruments": [
              {
                "ShortName": "SPECTRORADIOMETERS"
              }
            ]
          },
          {
            "ShortName": "AIRCRAFT",
            "Instruments": [
              {
                "ShortName": "SPECTRORADIOMETERS"
              }
            ]
          }
        ]
      }
    },
    {
      "meta": {
        "concept-type": "granule",
        "concept-id": "G1633153237-ORNL_DAAC",
        "revision-id": 1,
        "native-id": "OTTER_SE590_ULTRALT.6901007.prn",
        "provider-id": "ORNL_DAAC",
        "format": "application/echo10+xml",
        "revision-date": "2019-09-11T12:41:04Z"
      },
      "umm": {
        "TemporalExtent": {
          "RangeDateTime": {
            "BeginningDateTime": "1990-10-07T00:00:00.000Z",
            "EndingDateTime": "1990-10-07T00:00:00.000Z"
          }
        },
        "GranuleUR": "OTTER_SE590_ULTRALT.6901007.prn",
        "MeasuredParameters": [
          {
            "ParameterName": "REFLECTANCE"
          }
        ],
        "SpatialExtent": {
          "HorizontalSpatialDomain": {
            "Geometry": {
              "Points": [
                {
                  "Longitude": -121.331,
                  "Latitude": 44.2889
                }
              ]
            }
          }
        },
        "ProviderDates": [
          {
            "Date": "1994-07-24T00:00:00.000Z",
            "Type": "Insert"
          },
          {
            "Date": "2019-09-11T12:41:02.000Z",
            "Type": "Update"
          }
        ],
        "CollectionReference": {
          "ShortName": "OTTER_SE590_ULTRALT_86",
          "Version": "1"
        },
        "RelatedUrls": [
          {
            "URL": "https://daac.ornl.gov/daacdata/otter/spectra_se590_altitude/data/6901007.prn",
            "Type": "GET DATA",
            "Description": "This link provides direct download access to the granule."
          },
          {
            "URL": "https://daac.ornl.gov/OTTER/guides/SE590_Low_Altitude_Reflectance_Data.html",
            "Type": "VIEW RELATED INFORMATION",
            "Description": "ORNL DAAC Data Set Documentation"
          },
          {
            "URL": "https://dx.doi.org/10.3334/ORNLDAAC/86",
            "Type": "VIEW RELATED INFORMATION",
            "Description": "Data set Landing Page DOI URL"
          },
          {
            "URL": "https:/daac.ornl.gov/daacdata/otter/spectra_se590_altitude/comp/mccreigh.txt",
            "Type": "VIEW RELATED INFORMATION",
            "Description": "Data Set Documentation"
          },
          {
            "URL": "https:/daac.ornl.gov/daacdata/otter/spectra_se590_altitude/comp/se590.txt",
            "Type": "VIEW RELATED INFORMATION",
            "Description": "Data Set Documentation"
          },
          {
            "URL": "https:/daac.ornl.gov/daacdata/otter/spectra_se590_altitude/comp/SE590_Low_Altitude_Reflectance_Data.pdf",
            "Type": "VIEW RELATED INFORMATION",
            "Description": "Data Set Documentation"
          }
        ],
        "Projects": [
          {
            "ShortName": "Not provided",
            "Campaigns": [
              "OTTER"
            ]
          }
        ],
        "DataGranule": {
          "DayNightFlag": "Day",
          "ProductionDateTime": "1994-07-24T00:00:00.000Z",
          "ArchiveAndDistributionInformation": [
            {
              "Name": "Not provided",
              "Size": 0.005684,
              "SizeUnit": "NA"
            }
          ]
        },
        "Platforms": [
          {
            "ShortName": "FIELD INVESTIGATION",
            "Instruments": [
              {
                "ShortName": "SPECTRORADIOMETERS"
              }
            ]
          },
          {
            "ShortName": "AIRCRAFT",
            "Instruments": [
              {
                "ShortName": "SPECTRORADIOMETERS"
              }
            ]
          }
        ]
      }
    },
    {
      "meta": {
        "concept-type": "granule",
        "concept-id": "G1633153234-ORNL_DAAC",
        "revision-id": 1,
        "native-id": "OTTER_SE590_ULTRALT.4901008.prn",
        "provider-id": "ORNL_DAAC",
        "format": "application/echo10+xml",
        "revision-date": "2019-09-11T12:41:04Z"
      },
      "umm": {
        "TemporalExtent": {
          "RangeDateTime": {
            "BeginningDateTime": "1990-10-08T00:00:00.000Z",
            "EndingDateTime": "1990-10-08T00:00:00.000Z"
          }
        },
        "GranuleUR": "OTTER_SE590_ULTRALT.4901008.prn",
        "MeasuredParameters": [
          {
            "ParameterName": "REFLECTANCE"
          }
        ],
        "SpatialExtent": {
          "HorizontalSpatialDomain": {
            "Geometry": {
              "Points": [
                {
                  "Longitude": -121.841,
                  "Latitude": 44.4231
                }
              ]
            }
          }
        },
        "ProviderDates": [
          {
            "Date": "1994-07-24T00:00:00.000Z",
            "Type": "Insert"
          },
          {
            "Date": "2019-09-11T12:41:02.000Z",
            "Type": "Update"
          }
        ],
        "CollectionReference": {
          "ShortName": "OTTER_SE590_ULTRALT_86",
          "Version": "1"
        },
        "RelatedUrls": [
          {
            "URL": "https://daac.ornl.gov/daacdata/otter/spectra_se590_altitude/data/4901008.prn",
            "Type": "GET DATA",
            "Description": "This link provides direct download access to the granule."
          },
          {
            "URL": "https://daac.ornl.gov/OTTER/guides/SE590_Low_Altitude_Reflectance_Data.html",
            "Type": "VIEW RELATED INFORMATION",
            "Description": "ORNL DAAC Data Set Documentation"
          },
          {
            "URL": "https://dx.doi.org/10.3334/ORNLDAAC/86",
            "Type": "VIEW RELATED INFORMATION",
            "Description": "Data set Landing Page DOI URL"
          },
          {
            "URL": "https:/daac.ornl.gov/daacdata/otter/spectra_se590_altitude/comp/mccreigh.txt",
            "Type": "VIEW RELATED INFORMATION",
            "Description": "Data Set Documentation"
          },
          {
            "URL": "https:/daac.ornl.gov/daacdata/otter/spectra_se590_altitude/comp/se590.txt",
            "Type": "VIEW RELATED INFORMATION",
            "Description": "Data Set Documentation"
          },
          {
            "URL": "https:/daac.ornl.gov/daacdata/otter/spectra_se590_altitude/comp/SE590_Low_Altitude_Reflectance_Data.pdf",
            "Type": "VIEW RELATED INFORMATION",
            "Description": "Data Set Documentation"
          }
        ],
        "Projects": [
          {
            "ShortName": "Not provided",
            "Campaigns": [
              "OTTER"
            ]
          }
        ],
        "DataGranule": {
          "DayNightFlag": "Day",
          "ProductionDateTime": "1994-07-24T00:00:00.000Z",
          "ArchiveAndDistributionInformation": [
            {
              "Name": "Not provided",
              "Size": 0.005683,
              "SizeUnit": "NA"
            }
          ]
        },
        "Platforms": [
          {
            "ShortName": "FIELD INVESTIGATION",
            "Instruments": [
              {
                "ShortName": "SPECTRORADIOMETERS"
              }
            ]
          },
          {
            "ShortName": "AIRCRAFT",
            "Instruments": [
              {
                "ShortName": "SPECTRORADIOMETERS"
              }
            ]
          }
        ]
      }
    },
    {
      "meta": {
        "concept-type": "granule",
        "concept-id": "G1633153236-ORNL_DAAC",
        "revision-id": 1,
        "native-id": "OTTER_SE590_ULTRALT.2901011.prn",
        "provider-id": "ORNL_DAAC",
        "format": "application/echo10+xml",
        "revision-date": "2019-09-11T12:41:04Z"
      },
      "umm": {
        "TemporalExtent": {
          "RangeDateTime": {
            "BeginningDateTime": "1990-10-11T00:00:00.000Z",
            "EndingDateTime": "1990-10-11T00:00:00.000Z"
          }
        },
        "GranuleUR": "OTTER_SE590_ULTRALT.2901011.prn",
        "MeasuredParameters": [
          {
            "ParameterName": "REFLECTANCE"
          }
        ],
        "SpatialExtent": {
          "HorizontalSpatialDomain": {
            "Geometry": {
              "Points": [
                {
                  "Longitude": -123.27,
                  "Latitude": 44.6011
                }
              ]
            }
          }
        },
        "ProviderDates": [
          {
            "Date": "1994-07-24T00:00:00.000Z",
            "Type": "Insert"
          },
          {
            "Date": "2019-09-11T12:41:02.000Z",
            "Type": "Update"
          }
        ],
        "CollectionReference": {
          "ShortName": "OTTER_SE590_ULTRALT_86",
          "Version": "1"
        },
        "RelatedUrls": [
          {
            "URL": "https://daac.ornl.gov/daacdata/otter/spectra_se590_altitude/data/2901011.prn",
            "Type": "GET DATA",
            "Description": "This link provides direct download access to the granule."
          },
          {
            "URL": "https://daac.ornl.gov/OTTER/guides/SE590_Low_Altitude_Reflectance_Data.html",
            "Type": "VIEW RELATED INFORMATION",
            "Description": "ORNL DAAC Data Set Documentation"
          },
          {
            "URL": "https://dx.doi.org/10.3334/ORNLDAAC/86",
            "Type": "VIEW RELATED INFORMATION",
            "Description": "Data set Landing Page DOI URL"
          },
          {
            "URL": "https:/daac.ornl.gov/daacdata/otter/spectra_se590_altitude/comp/mccreigh.txt",
            "Type": "VIEW RELATED INFORMATION",
            "Description": "Data Set Documentation"
          },
          {
            "URL": "https:/daac.ornl.gov/daacdata/otter/spectra_se590_altitude/comp/se590.txt",
            "Type": "VIEW RELATED INFORMATION",
            "Description": "Data Set Documentation"
          },
          {
            "URL": "https:/daac.ornl.gov/daacdata/otter/spectra_se590_altitude/comp/SE590_Low_Altitude_Reflectance_Data.pdf",
            "Type": "VIEW RELATED INFORMATION",
            "Description": "Data Set Documentation"
          }
        ],
        "Projects": [
          {
            "ShortName": "Not provided",
            "Campaigns": [
              "OTTER"
            ]
          }
        ],
        "DataGranule": {
          "DayNightFlag": "Day",
          "ProductionDateTime": "1994-07-24T00:00:00.000Z",
          "ArchiveAndDistributionInformation": [
            {
              "Name": "Not provided",
              "Size": 0.005693,
              "SizeUnit": "NA"
            }
          ]
        },
        "Platforms": [
          {
            "ShortName": "FIELD INVESTIGATION",
            "Instruments": [
              {
                "ShortName": "SPECTRORADIOMETERS"
              }
            ]
          },
          {
            "ShortName": "AIRCRAFT",
            "Instruments": [
              {
                "ShortName": "SPECTRORADIOMETERS"
              }
            ]
          }
        ]
      }
    },
    {
      "meta": {
        "concept-type": "granule",
        "concept-id": "G1633153238-ORNL_DAAC",
        "revision-id": 1,
        "native-id": "OTTER_SE590_ULTRALT.3901020.prn",
        "provider-id": "ORNL_DAAC",
        "format": "application/echo10+xml",
        "revision-date": "2019-09-11T12:41:04Z"
      },
      "umm": {
        "TemporalExtent": {
          "RangeDateTime": {
            "BeginningDateTime": "1990-10-20T00:00:00.000Z",
            "EndingDateTime": "1990-10-20T00:00:00.000Z"
          }
        },
        "GranuleUR": "OTTER_SE590_ULTRALT.3901020.prn",
        "MeasuredParameters": [
          {
            "ParameterName": "REFLECTANCE"
          }
        ],
        "SpatialExtent": {
          "HorizontalSpatialDomain": {
            "Geometry": {
              "Points": [
                {
                  "Longitude": -122.606,
                  "Latitude": 44.6725
                }
              ]
            }
          }
        },
        "ProviderDates": [
          {
            "Date": "1994-07-24T00:00:00.000Z",
            "Type": "Insert"
          },
          {
            "Date": "2019-09-11T12:41:02.000Z",
            "Type": "Update"
          }
        ],
        "CollectionReference": {
          "ShortName": "OTTER_SE590_ULTRALT_86",
          "Version": "1"
        },
        "RelatedUrls": [
          {
            "URL": "https://daac.ornl.gov/daacdata/otter/spectra_se590_altitude/data/3901020.prn",
            "Type": "GET DATA",
            "Description": "This link provides direct download access to the granule."
          },
          {
            "URL": "https://daac.ornl.gov/OTTER/guides/SE590_Low_Altitude_Reflectance_Data.html",
            "Type": "VIEW RELATED INFORMATION",
            "Description": "ORNL DAAC Data Set Documentation"
          },
          {
            "URL": "https://dx.doi.org/10.3334/ORNLDAAC/86",
            "Type": "VIEW RELATED INFORMATION",
            "Description": "Data set Landing Page DOI URL"
          },
          {
            "URL": "https:/daac.ornl.gov/daacdata/otter/spectra_se590_altitude/comp/mccreigh.txt",
            "Type": "VIEW RELATED INFORMATION",
            "Description": "Data Set Documentation"
          },
          {
            "URL": "https:/daac.ornl.gov/daacdata/otter/spectra_se590_altitude/comp/se590.txt",
            "Type": "VIEW RELATED INFORMATION",
            "Description": "Data Set Documentation"
          },
          {
            "URL": "https:/daac.ornl.gov/daacdata/otter/spectra_se590_altitude/comp/SE590_Low_Altitude_Reflectance_Data.pdf",
            "Type": "VIEW RELATED INFORMATION",
            "Description": "Data Set Documentation"
          }
        ],
        "Projects": [
          {
            "ShortName": "Not provided",
            "Campaigns": [
              "OTTER"
            ]
          }
        ],
        "DataGranule": {
          "DayNightFlag": "Day",
          "ProductionDateTime": "1994-07-24T00:00:00.000Z",
          "ArchiveAndDistributionInformation": [
            {
              "Name": "Not provided",
              "Size": 0.005692,
              "SizeUnit": "NA"
            }
          ]
        },
        "Platforms": [
          {
            "ShortName": "FIELD INVESTIGATION",
            "Instruments": [
              {
                "ShortName": "SPECTRORADIOMETERS"
              }
            ]
          },
          {
            "ShortName": "AIRCRAFT",
            "Instruments": [
              {
                "ShortName": "SPECTRORADIOMETERS"
              }
            ]
          }
        ]
      }
    },
    {
      "meta": {
        "concept-type": "granule",
        "concept-id": "G1633153240-ORNL_DAAC",
        "revision-id": 1,
        "native-id": "OTTER_SE590_ULTRALT.1o910703.prn",
        "provider-id": "ORNL_DAAC",
        "format": "application/echo10+xml",
        "revision-date": "2019-09-11T12:41:05Z"
      },
      "umm": {
        "TemporalExtent": {
          "RangeDateTime": {
            "BeginningDateTime": "1991-07-03T00:00:00.000Z",
            "EndingDateTime": "1991-07-03T00:00:00.000Z"
          }
        },
        "GranuleUR": "OTTER_SE590_ULTRALT.1o910703.prn",
        "MeasuredParameters": [
          {
            "ParameterName": "REFLECTANCE"
          }
        ],
        "SpatialExtent": {
          "HorizontalSpatialDomain": {
            "Geometry": {
              "Points": [
                {
                  "Longitude": -123.922,
                  "Latitude": 45.0531
                }
              ]
            }
          }
        },
        "ProviderDates": [
          {
            "Date": "1994-07-24T00:00:00.000Z",
            "Type": "Insert"
          },
          {
            "Date": "2019-09-11T12:41:02.000Z",
            "Type": "Update"
          }
        ],
        "CollectionReference": {
          "ShortName": "OTTER_SE590_ULTRALT_86",
          "Version": "1"
        },
        "RelatedUrls": [
          {
            "URL": "https://daac.ornl.gov/daacdata/otter/spectra_se590_altitude/data/1o910703.prn",
            "Type": "GET DATA",
            "Description": "This link provides direct download access to the granule."
          },
          {
            "URL": "https://daac.ornl.gov/OTTER/guides/SE590_Low_Altitude_Reflectance_Data.html",
            "Type": "VIEW RELATED INFORMATION",
            "Description": "ORNL DAAC Data Set Documentation"
          },
          {
            "URL": "https://dx.doi.org/10.3334/ORNLDAAC/86",
            "Type": "VIEW RELATED INFORMATION",
            "Description": "Data set Landing Page DOI URL"
          },
          {
            "URL": "https:/daac.ornl.gov/daacdata/otter/spectra_se590_altitude/comp/mccreigh.txt",
            "Type": "VIEW RELATED INFORMATION",
            "Description": "Data Set Documentation"
          },
          {
            "URL": "https:/daac.ornl.gov/daacdata/otter/spectra_se590_altitude/comp/se590.txt",
            "Type": "VIEW RELATED INFORMATION",
            "Description": "Data Set Documentation"
          },
          {
            "URL": "https:/daac.ornl.gov/daacdata/otter/spectra_se590_altitude/comp/SE590_Low_Altitude_Reflectance_Data.pdf",
            "Type": "VIEW RELATED INFORMATION",
            "Description": "Data Set Documentation"
          }
        ],
        "Projects": [
          {
            "ShortName": "Not provided",
            "Campaigns": [
              "OTTER"
            ]
          }
        ],
        "DataGranule": {
          "DayNightFlag": "Day",
          "ProductionDateTime": "1994-07-24T00:00:00.000Z",
          "ArchiveAndDistributionInformation": [
            {
              "Name": "Not provided",
              "Size": 0.005699,
              "SizeUnit": "NA"
            }
          ]
        },
        "Platforms": [
          {
            "ShortName": "FIELD INVESTIGATION",
            "Instruments": [
              {
                "ShortName": "SPECTRORADIOMETERS"
              }
            ]
          },
          {
            "ShortName": "AIRCRAFT",
            "Instruments": [
              {
                "ShortName": "SPECTRORADIOMETERS"
              }
            ]
          }
        ]
      }
    },
    {
      "meta": {
        "concept-type": "granule",
        "concept-id": "G1633153241-ORNL_DAAC",
        "revision-id": 1,
        "native-id": "OTTER_SE590_ULTRALT.1A9101703.prn",
        "provider-id": "ORNL_DAAC",
        "format": "application/echo10+xml",
        "revision-date": "2019-09-11T12:41:04Z"
      },
      "umm": {
        "TemporalExtent": {
          "RangeDateTime": {
            "BeginningDateTime": "1991-07-03T00:00:00.000Z",
            "EndingDateTime": "1991-07-03T00:00:00.000Z"
          }
        },
        "GranuleUR": "OTTER_SE590_ULTRALT.1A9101703.prn",
        "MeasuredParameters": [
          {
            "ParameterName": "REFLECTANCE"
          }
        ],
        "SpatialExtent": {
          "HorizontalSpatialDomain": {
            "Geometry": {
              "Points": [
                {
                  "Longitude": -123.948,
                  "Latitude": 45.0664
                }
              ]
            }
          }
        },
        "ProviderDates": [
          {
            "Date": "1994-07-24T00:00:00.000Z",
            "Type": "Insert"
          },
          {
            "Date": "2019-09-11T12:41:02.000Z",
            "Type": "Update"
          }
        ],
        "CollectionReference": {
          "ShortName": "OTTER_SE590_ULTRALT_86",
          "Version": "1"
        },
        "RelatedUrls": [
          {
            "URL": "https://daac.ornl.gov/daacdata/otter/spectra_se590_altitude/data/1A9101703.prn",
            "Type": "GET DATA",
            "Description": "This link provides direct download access to the granule."
          },
          {
            "URL": "https://daac.ornl.gov/OTTER/guides/SE590_Low_Altitude_Reflectance_Data.html",
            "Type": "VIEW RELATED INFORMATION",
            "Description": "ORNL DAAC Data Set Documentation"
          },
          {
            "URL": "https://dx.doi.org/10.3334/ORNLDAAC/86",
            "Type": "VIEW RELATED INFORMATION",
            "Description": "Data set Landing Page DOI URL"
          },
          {
            "URL": "https:/daac.ornl.gov/daacdata/otter/spectra_se590_altitude/comp/mccreigh.txt",
            "Type": "VIEW RELATED INFORMATION",
            "Description": "Data Set Documentation"
          },
          {
            "URL": "https:/daac.ornl.gov/daacdata/otter/spectra_se590_altitude/comp/se590.txt",
            "Type": "VIEW RELATED INFORMATION",
            "Description": "Data Set Documentation"
          },
          {
            "URL": "https:/daac.ornl.gov/daacdata/otter/spectra_se590_altitude/comp/SE590_Low_Altitude_Reflectance_Data.pdf",
            "Type": "VIEW RELATED INFORMATION",
            "Description": "Data Set Documentation"
          }
        ],
        "Projects": [
          {
            "ShortName": "Not provided",
            "Campaigns": [
              "OTTER"
            ]
          }
        ],
        "DataGranule": {
          "DayNightFlag": "Day",
          "ProductionDateTime": "1994-07-24T00:00:00.000Z",
          "ArchiveAndDistributionInformation": [
            {
              "Name": "Not provided",
              "Size": 0.005699,
              "SizeUnit": "NA"
            }
          ]
        },
        "Platforms": [
          {
            "ShortName": "FIELD INVESTIGATION",
            "Instruments": [
              {
                "ShortName": "SPECTRORADIOMETERS"
              }
            ]
          },
          {
            "ShortName": "AIRCRAFT",
            "Instruments": [
              {
                "ShortName": "SPECTRORADIOMETERS"
              }
            ]
          }
        ]
      }
    }
  ]
}