{
  "hits": 1,
  "took": 13,
  "items": [
    {
      "meta": {
        "concept-type": "granule",
        "concept-id": "G1422754682-ORNL_DAAC",
        "revision-id": 1,
        "native-id": "BOREAS_TF11TFX.tf11_tower_flux.dat",
        "provider-id": "ORNL_DAAC",
        "format": "application/echo10+xml",
        "revision-date": "2017-09-28T16:35:51Z"
      },
      "umm": {
        "TemporalExtent": {
          "RangeDateTime": {
            "BeginningDateTime": "1993-08-23T00:00:00.000Z",
            "EndingDateTime": "1995-10-09T00:00:00.000Z"
          }
        },
        "GranuleUR": "BOREAS_TF11TFX.tf11_tower_flux.dat",
        "MeasuredParameters": [
          {
            "ParameterName": "CARBON DIOXIDE"
          },
          {
            "ParameterName": "METHANE"
          },
          {
            "ParameterName": "HUMIDITY"
          },
          {
            "ParameterName": "WATER DEPTH"
          },
          {
            "ParameterName": "SURFACE PRESSURE"
          },
          {
            "ParameterName": "HEAT FLUX"
          },
          {
            "ParameterName": "NET RADIATION"
          },
          {
            "ParameterName": "REFLECTANCE"
          },
          {
            "ParameterName": "SOLAR IRRADIANCE"
          },
          {
            "ParameterName": "SURFACE WINDS"
          },
          {
            "ParameterName": "PHOTOSYNTHETICALLY ACTIVE RADIATION"
          },
          {
            "ParameterName": "SOIL HEAT BUDGET"
          }
        ],
        "SpatialExtent": {
          "HorizontalSpatialDomain": {
            "Geometry": {
              "Points": [
                {
                  "Longitude": -104.618,
                  "Latitude": 53.8021
                }
              ]
            }
          }
        },
        "ProviderDates": [
          {
            "Date": "1999-01-30T00:00:00.000Z",
            "Type": "Insert"
          },
          {
            "Date": "1999-01-30T00:00:00.000Z",
            "Type": "Update"
          }
        ],
        "CollectionReference": {
          "ShortName": "BOREAS_TF11TFX_373",
          "Version": "1"
        },
        "RelatedUrls": [
          {
            "URL": "https://daac.ornl.gov/daacdata/boreas/TF/tf11tfx/data/tf11_tower_flux.dat",
            "Type": "GET DATA",
            "Description": "This link provides direct download access to the granule."
          },
          {
            "URL": "https://daac.ornl.gov/BOREAS/guides/TF11_Fen_Flux.html",
            "Type": "VIEW RELATED INFORMATION",
            "Description": "ORNL DAAC Data Set Documentation"
          },
          {
            "URL": "https://dx.doi.org/doi:10.3334/ORNLDAAC/373",
            "Type": "VIEW RELATED INFORMATION",
            "Description": "Data set Landing Page DOI URL"
          },
          {
            "URL": "https:/daac.ornl.gov/daacdata/boreas/TF/tf11tfx/comp/tf11tfx.def",
            "Type": "VIEW RELATED INFORMATION",
            "Description": "Data Set Documentation"
          },
          {
            "URL": "https:/daac.ornl.gov/daacdata/boreas/TF/tf11tfx/comp/TF11_Fen_Flux.doc",
            "Type": "VIEW RELATED INFORMATION",
            "Description": "Data Set Documentation"
          },
          {
            "URL": "https:/daac.ornl.gov/daacdata/boreas/TF/tf11tfx/comp/TF11_Fen_Flux.pdf",
            "Type": "VIEW RELATED INFORMATION",
            "Description": "Data Set Documentation"
          },
          {
            "URL": "https:/daac.ornl.gov/daacdata/boreas/TF/tf11tfx/comp/TF11_Fen_Flux.txt",
            "Type": "VIEW RELATED INFORMATION",
            "Description": "Data Set Documentation"
          }
        ],
        "Projects": [
          {
            "ShortName": "Not provided",
            "Campaigns": [
              "BOREAS"
            ]
          }
        ],
        "DataGranule": {
          "DayNightFlag": "Day",
          "ProductionDateTime": "1999-01-30T00:00:00.000Z",
          "ArchiveAndDistributionInformation": [
            {
              "Name": "Not provided",
              "Size": 2.470885,
              "SizeUnit": "NA"
            }
          ]
        },
        "Platforms": [
          {
            "ShortName": "FIXED OBSERVATION STATIONS",
            "Instruments": [
              {
                "ShortName": "WATER LEVEL GAUGES"
              },
              {
                "ShortName": "SOIL HEAT FLUX TRANSDUCER"
              },
              {
                "ShortName": "LICOR QUANTUM SENSOR"
              },
              {
                "ShortName": "PYRANOMETERS"
              },
              {
                "ShortName": "NET RADIOMETERS"
              },
              {
                "ShortName": "IRGA"
              },
              {
                "ShortName": "HUMIDITY SENSORS"
              },
              {
                "ShortName": "EDDY CORRELATION DEVICES"
              },
              {
                "ShortName": "ANEROID PRESSURE SENSOR"
              },
              {
                "ShortName": "ANEMOMETERS"
              }
            ]
          },
          {
            "ShortName": "LABORATORY",
            "Instruments": [
              {
                "ShortName": "TUNABLE DIODE LASER"
              }
            ]
          }
        ]
      }
    }
  ]
}